{"age": "33", "gender": "male", "comments": [{"created_at": 1538736095, "text": "Untung aku ga ketipu. Liat mukanya bengep begitu ketahuan banget abis suntik Botox murahan / oplas. Kalo digebukin Paling ga bagian Mata Ada yg biru atau bekas Darah di bola mata. Ratu Halu Indonesia RS", "user_id": 1084260119, "status": "Active", "bit_flags": 0, "content_type": "comment", "inline_composer_display_condition": "never", "has_liked_comment": false, "created_at_utc": 1538736095, "user": {"is_verified": false, "pk": 1084260119, "username": "valjames888", "is_private": false, "profile_pic_id": "1599889276924183302_1084260119", "full_name": "Valiant Gracian James S.", "profile_pic_url": "https://scontent-sit4-1.cdninstagram.com/vp/df2bcf5a636fc60deb0f0a51cbcced2d/5C4E8484/t51.2885-19/s150x150/21480002_172046016699435_6834253460062339072_a.jpg"}, "pk": 17958382636193556, "did_report_as_spam": false, "comment_like_count": 0, "type": 0}, {"created_at": 1538729368, "text": "Mantap mas Robert. Tuhan Memberkati", "user_id": 1562323589, "status": "Active", "bit_flags": 0, "content_type": "comment", "inline_composer_display_condition": "never", "has_liked_comment": false, "created_at_utc": 1538729368, "user": {"is_verified": false, "pk": 1562323589, "username": "benn_shu90", "is_private": true, "profile_pic_id": "1562885364540353408_1562323589", "full_name": "#bPs", "profile_pic_url": "https://scontent-sit4-1.cdninstagram.com/vp/e9eb506a79a2f9e371b5ce34db686457/5C5048F2/t51.2885-19/s150x150/20213942_905664892922558_1441242573287981056_a.jpg"}, "pk": 17912828935234046, "did_report_as_spam": false, "comment_like_count": 0, "type": 0}, {"created_at": 1538726836, "text": "Keren", "user_id": 3019580951, "status": "Active", "bit_flags": 0, "content_type": "comment", "inline_composer_display_condition": "never", "has_liked_comment": false, "created_at_utc": 1538726836, "user": {"is_verified": false, "pk": 3019580951, "username": "maulanaichsan2370", "is_private": false, "profile_pic_id": "1875518316355536290_3019580951", "full_name": "Maulana Ichsan |", "profile_pic_url": "https://scontent-sit4-1.cdninstagram.com/vp/f04166d74e8368dedd70555cc2209d04/5C50BF5E/t51.2885-19/s150x150/41182861_467234553787451_1556797298292293632_n.jpg"}, "pk": 17984835652050630, "did_report_as_spam": false, "comment_like_count": 0, "type": 0}, {"created_at": 1538717507, "text": "Karna ada nafa urbach gue jd kenal ini presenter. \ud83e\udd23\ud83e\udd23", "user_id": 531271183, "status": "Active", "bit_flags": 0, "content_type": "comment", "inline_composer_display_condition": "never", "has_liked_comment": false, "created_at_utc": 1538717507, "user": {"is_verified": false, "pk": 531271183, "username": "zerlinda_giovanni", "is_private": false, "profile_pic_id": "1871869049198244159_531271183", "full_name": "Zerlinda Giovanni", "profile_pic_url": "https://scontent-sit4-1.cdninstagram.com/vp/7b8047aed7584fdfb03c019bf237de27/5C562888/t51.2885-19/s150x150/40773268_277410853095674_4591655519319490560_n.jpg"}, "pk": 17984826187056071, "did_report_as_spam": false, "comment_like_count": 0, "type": 0}, {"created_at": 1538714982, "text": "ini nih pembaca berita idola gua dari semua pembaca berita yg pernah gua tonton @robetbet  sukses selalu ya kokoh... dan God bless you always...\ud83d\ude07\ud83d\ude07", "user_id": 4070135487, "status": "Active", "bit_flags": 0, "content_type": "comment", "inline_composer_display_condition": "never", "has_liked_comment": false, "created_at_utc": 1538714982, "user": {"is_verified": false, "pk": 4070135487, "username": "domry_koree", "is_private": false, "profile_pic_id": "1886379525241524509_4070135487", "full_name": "domry koree", "profile_pic_url": "https://scontent-sit4-1.cdninstagram.com/vp/9cdd95108d7d95e0ebe32acec5b328de/5C4A8DF9/t51.2885-19/s150x150/41947689_352898905276235_4639810078461919232_n.jpg"}, "pk": 17979667630068735, "did_report_as_spam": false, "comment_like_count": 0, "type": 0}, {"created_at": 1538710968, "text": "widiwww", "user_id": 537833997, "status": "Active", "bit_flags": 0, "content_type": "comment", "inline_composer_display_condition": "never", "has_liked_comment": false, "created_at_utc": 1538710968, "user": {"is_verified": false, "pk": 537833997, "username": "naclevity", "latest_reel_media": 1539611280, "is_private": false, "profile_pic_id": "1881850388417958702_537833997", "full_name": "Nathalia Surya", "profile_pic_url": "https://scontent-sit4-1.cdninstagram.com/vp/1e22a6927610b134c190701733f83f1b/5C4E7335/t51.2885-19/s150x150/41728642_324886338332465_7148418918921535488_n.jpg"}, "pk": 17878637677278705, "did_report_as_spam": false, "comment_like_count": 0, "type": 0}, {"created_at": 1538710901, "text": "@robetbet good", "user_id": 8903972564, "status": "Active", "bit_flags": 0, "content_type": "comment", "inline_composer_display_condition": "never", "has_liked_comment": false, "created_at_utc": 1538710901, "user": {"is_verified": false, "pk": 8903972564, "username": "natasiays518", "is_private": false, "profile_pic_id": "1881668033039111348_8903972564", "full_name": "Natasia.Y.S", "profile_pic_url": "https://scontent-sit4-1.cdninstagram.com/vp/f533a087b4e2b183bc911a0bfe111e61/5C3F0911/t51.2885-19/s150x150/42003217_277196719587847_5131328373494120448_n.jpg"}, "pk": 17878395586272852, "did_report_as_spam": false, "comment_like_count": 0, "type": 0}, {"created_at": 1538709213, "text": "#raisameetsutopo #sutopomeetraisa", "user_id": 25485149, "status": "Active", "bit_flags": 0, "content_type": "comment", "inline_composer_display_condition": "never", "has_liked_comment": false, "created_at_utc": 1538709213, "user": {"is_verified": false, "pk": 25485149, "username": "robetbet", "latest_reel_media": 1539605102, "is_private": false, "profile_pic_id": "1829050840875530907_25485149", "full_name": "Robert Harianto", "profile_pic_url": "https://scontent-sit4-1.cdninstagram.com/vp/ce105b1c61ad66f21b1bf6fe86f43bef/5C527CAE/t51.2885-19/s150x150/37130754_218502508992672_8006267335545454592_n.jpg"}, "pk": 17986524079034906, "did_report_as_spam": false, "comment_like_count": 0, "type": 0}, {"created_at": 1538925741, "text": "@naclevity thank you \ud83d\ude4f", "user_id": 25485149, "status": "Active", "bit_flags": 0, "content_type": "comment", "inline_composer_display_condition": "never", "created_at_utc": 1538925741, "user": {"is_verified": false, "pk": 25485149, "username": "robetbet", "latest_reel_media": 1539605102, "is_private": false, "profile_pic_id": "1829050840875530907_25485149", "full_name": "Robert Harianto", "profile_pic_url": "https://scontent-sit4-1.cdninstagram.com/vp/ce105b1c61ad66f21b1bf6fe86f43bef/5C527CAE/t51.2885-19/s150x150/37130754_218502508992672_8006267335545454592_n.jpg"}, "pk": 17969049868127976, "did_report_as_spam": false, "type": 2}, {"created_at": 1538925733, "text": "@barrylikumahuwa \ud83d\ude4c\ud83d\ude4c\ud83d\ude4c", "user_id": 25485149, "status": "Active", "bit_flags": 0, "content_type": "comment", "inline_composer_display_condition": "never", "created_at_utc": 1538925733, "user": {"is_verified": false, "pk": 25485149, "username": "robetbet", "latest_reel_media": 1539605102, "is_private": false, "profile_pic_id": "1829050840875530907_25485149", "full_name": "Robert Harianto", "profile_pic_url": "https://scontent-sit4-1.cdninstagram.com/vp/ce105b1c61ad66f21b1bf6fe86f43bef/5C527CAE/t51.2885-19/s150x150/37130754_218502508992672_8006267335545454592_n.jpg"}, "pk": 17972114857108663, "did_report_as_spam": false, "type": 2}, {"created_at": 1538787201, "text": "Keren rolexnya", "user_id": 7762216766, "status": "Active", "bit_flags": 0, "content_type": "comment", "inline_composer_display_condition": "never", "has_liked_comment": false, "created_at_utc": 1538787201, "user": {"is_verified": false, "pk": 7762216766, "username": "luxwatches_jakarta", "latest_reel_media": 1539616881, "is_private": false, "profile_pic_id": "1875430204160233949_7762216766", "full_name": "Luxury Watches Jakarta", "profile_pic_url": "https://scontent-sit4-1.cdninstagram.com/vp/31e484dc0ea644d6d9dec53430809553/5C59D0CF/t51.2885-19/s150x150/41591074_304340180395780_4296599903263522816_n.jpg"}, "pk": 17986146112017931, "did_report_as_spam": false, "comment_like_count": 0, "type": 0}, {"created_at": 1538682428, "text": "Dm. To robert", "user_id": 7182722162, "status": "Active", "bit_flags": 0, "content_type": "comment", "inline_composer_display_condition": "never", "has_liked_comment": false, "created_at_utc": 1538682428, "user": {"is_verified": false, "pk": 7182722162, "username": "marno_8890", "is_private": false, "profile_pic_id": "1741209833842893171_7182722162", "full_name": "sumarno", "profile_pic_url": "https://scontent-sit4-1.cdninstagram.com/vp/4cc01ab3bba857d407230c43e5b96b50/5C3D41F4/t51.2885-19/s150x150/29094615_354845935001363_3790206727736000512_n.jpg"}, "pk": 17985773245011169, "did_report_as_spam": false, "comment_like_count": 0, "type": 0}, {"created_at": 1538665411, "text": "\ud83d\ude4c\ud83c\udffe\ud83d\ude4c\ud83c\udffe", "user_id": 3634712, "status": "Active", "bit_flags": 0, "content_type": "comment", "inline_composer_display_condition": "never", "has_liked_comment": false, "created_at_utc": 1538665411, "user": {"is_verified": false, "pk": 3634712, "username": "barrylikumahuwa", "latest_reel_media": 1539602077, "is_private": false, "profile_pic_id": "1653560012579861213_3634712", "full_name": "Barry Likumahuwa", "profile_pic_url": "https://scontent-sit4-1.cdninstagram.com/vp/fcdc4f16f40d0bbd944a80c153e0e8cd/5C46898E/t51.2885-19/s150x150/23734277_152601378603646_1372135093501427712_n.jpg"}, "pk": 17986653166005038, "did_report_as_spam": false, "comment_like_count": 1, "type": 0}, {"created_at": 1538663064, "text": "Kalo ak pingin peluk km koh @robetbet \ud83d\ude1b\ud83d\ude1b\ud83d\ude02\ud83d\ude02", "user_id": 1949398727, "status": "Active", "bit_flags": 0, "content_type": "comment", "inline_composer_display_condition": "never", "has_liked_comment": false, "created_at_utc": 1538663064, "user": {"is_verified": false, "pk": 1949398727, "username": "lydia_tjoeng_", "is_private": true, "profile_pic_id": "1889279659427569116_1949398727", "full_name": "cingtwice", "profile_pic_url": "https://scontent-sit4-1.cdninstagram.com/vp/5b0d82cf94e9370e7e2adad1d468c42c/5C3FB455/t51.2885-19/s150x150/42614300_665300050530205_8427972431829794816_n.jpg"}, "pk": 17908002754245247, "did_report_as_spam": false, "comment_like_count": 0, "type": 0}, {"created_at": 1538662338, "text": "Yang begini yang perlu dilestarikan. mantap ko \ud83d\udc4d\ud83d\udc4d", "user_id": 537833997, "status": "Active", "bit_flags": 0, "content_type": "comment", "inline_composer_display_condition": "never", "has_liked_comment": false, "created_at_utc": 1538662338, "user": {"is_verified": false, "pk": 537833997, "username": "naclevity", "latest_reel_media": 1539611280, "is_private": false, "profile_pic_id": "1881850388417958702_537833997", "full_name": "Nathalia Surya", "profile_pic_url": "https://scontent-sit4-1.cdninstagram.com/vp/1e22a6927610b134c190701733f83f1b/5C4E7335/t51.2885-19/s150x150/41728642_324886338332465_7148418918921535488_n.jpg"}, "pk": 17913123139232555, "did_report_as_spam": false, "comment_like_count": 1, "type": 0}, {"created_at": 1538645970, "text": "\ud83d\udc4d\ud83d\udc4d\ud83d\udc4d\ud83d\udc4d\ud83d\udc4d\ud83d\udc4d\ud83d\udc4d\ud83d\udc4d\ud83d\udc4d\ud83d\udc4d", "user_id": 2972128126, "status": "Active", "bit_flags": 0, "content_type": "comment", "inline_composer_display_condition": "never", "has_liked_comment": false, "created_at_utc": 1538645970, "user": {"is_verified": false, "pk": 2972128126, "username": "ian.budi", "is_private": false, "profile_pic_id": "1877639834132877384_2972128126", "full_name": "Budi Ian", "profile_pic_url": "https://scontent-sit4-1.cdninstagram.com/vp/a5f4c379584f7c52733d6cdd3a0436f0/5C5DF296/t51.2885-19/s150x150/41945967_1988291284547829_4983681395156058112_n.jpg"}, "pk": 17925043105202314, "did_report_as_spam": false, "comment_like_count": 0, "type": 0}, {"created_at": 1538645752, "text": "my hero..my divo", "user_id": 4620231202, "status": "Active", "bit_flags": 0, "content_type": "comment", "inline_composer_display_condition": "never", "has_liked_comment": false, "created_at_utc": 1538645752, "user": {"is_verified": false, "pk": 4620231202, "username": "tristantarta", "is_private": false, "profile_pic_id": "1447884425933073971_4620231202", "full_name": "Bambang Tristantarta", "profile_pic_url": "https://scontent-sit4-1.cdninstagram.com/vp/f4c3ad4427d0c4479c06bf8b3ec28f0d/5C535492/t51.2885-19/s150x150/16584922_1850964648508250_1356841011313115136_a.jpg"}, "pk": 17895716509250566, "did_report_as_spam": false, "comment_like_count": 1, "type": 0}, {"created_at": 1538641334, "text": "@robetbet hanya lht org utan aja di Kalimantan, yg lain ada lht ?", "user_id": 8903972564, "status": "Active", "bit_flags": 0, "content_type": "comment", "inline_composer_display_condition": "never", "has_liked_comment": false, "created_at_utc": 1538641334, "user": {"is_verified": false, "pk": 8903972564, "username": "natasiays518", "is_private": false, "profile_pic_id": "1881668033039111348_8903972564", "full_name": "Natasia.Y.S", "profile_pic_url": "https://scontent-sit4-1.cdninstagram.com/vp/f533a087b4e2b183bc911a0bfe111e61/5C3F0911/t51.2885-19/s150x150/42003217_277196719587847_5131328373494120448_n.jpg"}, "pk": 17986321084033018, "did_report_as_spam": false, "comment_like_count": 0, "type": 0}, {"created_at": 1538640923, "text": "Jd hrs sadari tdk blh mengganggu hutan, binatang2 dan tumbuhan yg di hutan juga makhluk seperti kita", "user_id": 8903972564, "status": "Active", "bit_flags": 0, "content_type": "comment", "inline_composer_display_condition": "never", "has_liked_comment": false, "created_at_utc": 1538640923, "user": {"is_verified": false, "pk": 8903972564, "username": "natasiays518", "is_private": false, "profile_pic_id": "1881668033039111348_8903972564", "full_name": "Natasia.Y.S", "profile_pic_url": "https://scontent-sit4-1.cdninstagram.com/vp/f533a087b4e2b183bc911a0bfe111e61/5C3F0911/t51.2885-19/s150x150/42003217_277196719587847_5131328373494120448_n.jpg"}, "pk": 17959365769192516, "did_report_as_spam": false, "comment_like_count": 0, "type": 0}, {"created_at": 1538640838, "text": "@robetbet pelukan dgn org utan ttp cool", "user_id": 8903972564, "status": "Active", "bit_flags": 0, "content_type": "comment", "inline_composer_display_condition": "never", "has_liked_comment": false, "created_at_utc": 1538640838, "user": {"is_verified": false, "pk": 8903972564, "username": "natasiays518", "is_private": false, "profile_pic_id": "1881668033039111348_8903972564", "full_name": "Natasia.Y.S", "profile_pic_url": "https://scontent-sit4-1.cdninstagram.com/vp/f533a087b4e2b183bc911a0bfe111e61/5C3F0911/t51.2885-19/s150x150/42003217_277196719587847_5131328373494120448_n.jpg"}, "pk": 17953320652160991, "did_report_as_spam": false, "comment_like_count": 0, "type": 0}, {"created_at": 1538640788, "text": "Skg hutan ada yg dibabat atau yg lainnya adlh manusia yg lakukan, hingga binatang2 tdk ada tmpt tinggal.", "user_id": 8903972564, "status": "Active", "bit_flags": 0, "content_type": "comment", "inline_composer_display_condition": "never", "has_liked_comment": false, "created_at_utc": 1538640788, "user": {"is_verified": false, "pk": 8903972564, "username": "natasiays518", "is_private": false, "profile_pic_id": "1881668033039111348_8903972564", "full_name": "Natasia.Y.S", "profile_pic_url": "https://scontent-sit4-1.cdninstagram.com/vp/f533a087b4e2b183bc911a0bfe111e61/5C3F0911/t51.2885-19/s150x150/42003217_277196719587847_5131328373494120448_n.jpg"}, "pk": 17963573875093444, "did_report_as_spam": false, "comment_like_count": 0, "type": 0}, {"created_at": 1538891023, "text": "Bantu follow mas ig saya thq", "user_id": 4387757302, "status": "Active", "bit_flags": 0, "content_type": "comment", "inline_composer_display_condition": "never", "has_liked_comment": false, "created_at_utc": 1538891023, "user": {"is_verified": false, "pk": 4387757302, "username": "donny_rich1", "is_private": true, "profile_pic_id": "1783470990443902974_4387757302", "full_name": "Donny Richwan", "profile_pic_url": "https://scontent-sit4-1.cdninstagram.com/vp/7c7e6a3df434ffdc8e52941b3a3a3ccd/5C564E13/t51.2885-19/s150x150/32145427_1998741637121577_511565965419347968_n.jpg"}, "pk": 17855777344289285, "did_report_as_spam": false, "comment_like_count": 0, "type": 0}, {"created_at": 1538030363, "text": "\ud83e\udd13", "user_id": 8600240597, "status": "Active", "bit_flags": 0, "content_type": "comment", "inline_composer_display_condition": "never", "has_liked_comment": false, "created_at_utc": 1538030363, "user": {"is_verified": false, "pk": 8600240597, "username": "pijat_priajkts", "is_private": false, "profile_pic_id": "1871082207742055608_8600240597", "full_name": "pijat pria jkts", "profile_pic_url": "https://scontent-sit4-1.cdninstagram.com/vp/99f230c80722d3c78183dc332a15a8de/5C3CC7AC/t51.2885-19/s150x150/40619662_545430125915817_1957845079351623680_n.jpg"}, "pk": 17852827450288622, "did_report_as_spam": false, "comment_like_count": 0, "type": 0}, {"created_at": 1537975359, "text": "Ngeliatin apa ka @robetbet sampe melongo. Lol", "user_id": 2133562897, "status": "Active", "bit_flags": 0, "content_type": "comment", "inline_composer_display_condition": "never", "has_liked_comment": false, "created_at_utc": 1537975359, "user": {"is_verified": false, "pk": 2133562897, "username": "deripresto", "is_private": true, "profile_pic_id": "1890101569123629057_2133562897", "full_name": "I am Deri", "profile_pic_url": "https://scontent-sit4-1.cdninstagram.com/vp/285395d643c85c3c8fd02be13d6a5635/5C480462/t51.2885-19/s150x150/42519841_1082537018572617_97548667321319424_n.jpg"}, "pk": 17947680988169713, "did_report_as_spam": false, "comment_like_count": 0, "type": 0}, {"created_at": 1537949212, "text": "Lebih macho dgn brewok yg baru tumbuh \ud83d\ude0a", "user_id": 5623376958, "status": "Active", "bit_flags": 0, "content_type": "comment", "inline_composer_display_condition": "never", "has_liked_comment": false, "created_at_utc": 1537949212, "user": {"is_verified": false, "pk": 5623376958, "username": "kokocentraljava", "is_private": false, "profile_pic_id": "1543542966430158387_5623376958", "full_name": "Andy Setiawan", "profile_pic_url": "https://scontent-sit4-1.cdninstagram.com/vp/cb6f14900bf367aa037c2640535687d7/5C46FBEC/t51.2885-19/s150x150/19425184_646041752257860_3575429294597341184_a.jpg"}, "pk": 17983583059037362, "did_report_as_spam": false, "comment_like_count": 0, "type": 0}, {"created_at": 1537947560, "text": "You look casual with nice sport shoes", "user_id": 8903972564, "status": "Active", "bit_flags": 0, "content_type": "comment", "inline_composer_display_condition": "never", "has_liked_comment": false, "created_at_utc": 1537947560, "user": {"is_verified": false, "pk": 8903972564, "username": "natasiays518", "is_private": false, "profile_pic_id": "1881668033039111348_8903972564", "full_name": "Natasia.Y.S", "profile_pic_url": "https://scontent-sit4-1.cdninstagram.com/vp/f533a087b4e2b183bc911a0bfe111e61/5C3F0911/t51.2885-19/s150x150/42003217_277196719587847_5131328373494120448_n.jpg"}, "pk": 17891669416261512, "did_report_as_spam": false, "comment_like_count": 0, "type": 0}, {"created_at": 1537887323, "text": "@ganindrabimo sama bro kaya gua, cuma bedanya enggk ada yg mau kasih gratisan ke gua \ud83d\ude04", "user_id": 25485149, "status": "Active", "bit_flags": 0, "content_type": "comment", "inline_composer_display_condition": "never", "created_at_utc": 1537887323, "user": {"is_verified": false, "pk": 25485149, "username": "robetbet", "latest_reel_media": 1539605102, "is_private": false, "profile_pic_id": "1829050840875530907_25485149", "full_name": "Robert Harianto", "profile_pic_url": "https://scontent-sit4-1.cdninstagram.com/vp/ce105b1c61ad66f21b1bf6fe86f43bef/5C527CAE/t51.2885-19/s150x150/37130754_218502508992672_8006267335545454592_n.jpg"}, "pk": 17952744556152495, "did_report_as_spam": false, "type": 2}, {"created_at": 1537886337, "text": "@robetbet salah... karna gw gratisan anaknya \ud83d\ude1b", "user_id": 1505725310, "status": "Active", "bit_flags": 0, "content_type": "comment", "inline_composer_display_condition": "never", "created_at_utc": 1537886337, "user": {"is_verified": true, "pk": 1505725310, "username": "ganindrabimo", "latest_reel_media": 1539580920, "is_private": false, "profile_pic_id": "1813076836297769075_1505725310", "full_name": "Ganindra Bimo", "profile_pic_url": "https://scontent-sit4-1.cdninstagram.com/vp/cd1b3c17dcaa1cc6daec2534fa0934de/5C51F89E/t51.2885-19/s150x150/35616835_2598656973692821_7221235193162498048_n.jpg"}, "pk": 17920840192208949, "did_report_as_spam": false, "has_translation": true, "type": 2}, {"created_at": 1537886075, "text": "@vrkvngel thanks! You have a great feeds too", "user_id": 25485149, "status": "Active", "bit_flags": 0, "content_type": "comment", "inline_composer_display_condition": "never", "created_at_utc": 1537886075, "user": {"is_verified": false, "pk": 25485149, "username": "robetbet", "latest_reel_media": 1539605102, "is_private": false, "profile_pic_id": "1829050840875530907_25485149", "full_name": "Robert Harianto", "profile_pic_url": "https://scontent-sit4-1.cdninstagram.com/vp/ce105b1c61ad66f21b1bf6fe86f43bef/5C527CAE/t51.2885-19/s150x150/37130754_218502508992672_8006267335545454592_n.jpg"}, "pk": 17939901952198169, "did_report_as_spam": false, "type": 2}, {"created_at": 1537886061, "text": "@ganindrabimo kalau cicilan motor lo = cicilan rumah \ud83d\ude04", "user_id": 25485149, "status": "Active", "bit_flags": 0, "content_type": "comment", "inline_composer_display_condition": "never", "created_at_utc": 1537886061, "user": {"is_verified": false, "pk": 25485149, "username": "robetbet", "latest_reel_media": 1539605102, "is_private": false, "profile_pic_id": "1829050840875530907_25485149", "full_name": "Robert Harianto", "profile_pic_url": "https://scontent-sit4-1.cdninstagram.com/vp/ce105b1c61ad66f21b1bf6fe86f43bef/5C527CAE/t51.2885-19/s150x150/37130754_218502508992672_8006267335545454592_n.jpg"}, "pk": 17981151364045386, "did_report_as_spam": false, "type": 2}, {"created_at": 1537883506, "text": "HAHAHAHA ! Boss obet cicilan spatu = cicilan motor", "user_id": 1505725310, "status": "Active", "bit_flags": 0, "content_type": "comment", "inline_composer_display_condition": "never", "has_liked_comment": false, "created_at_utc": 1537883506, "user": {"is_verified": true, "pk": 1505725310, "username": "ganindrabimo", "latest_reel_media": 1539580920, "is_private": false, "profile_pic_id": "1813076836297769075_1505725310", "full_name": "Ganindra Bimo", "profile_pic_url": "https://scontent-sit4-1.cdninstagram.com/vp/cd1b3c17dcaa1cc6daec2534fa0934de/5C51F89E/t51.2885-19/s150x150/35616835_2598656973692821_7221235193162498048_n.jpg"}, "pk": 17991606544042251, "did_report_as_spam": false, "has_translation": true, "comment_like_count": 1, "type": 0}, {"created_at": 1537877345, "text": "Nice pict", "user_id": 3293018227, "status": "Active", "bit_flags": 0, "content_type": "comment", "inline_composer_display_condition": "never", "has_liked_comment": false, "created_at_utc": 1537877345, "user": {"is_verified": false, "pk": 3293018227, "username": "batik_lochatara_kediri", "is_private": false, "profile_pic_id": "1800701366882362027_3293018227", "full_name": "Batik Lochatara Kediri", "profile_pic_url": "https://scontent-sit4-1.cdninstagram.com/vp/ea7cd3d22bf4299e8d3f2efa64cd05c0/5C4C7488/t51.2885-19/s150x150/33817523_173597226665297_6198578710908502016_n.jpg"}, "pk": 17982008740057434, "did_report_as_spam": false, "comment_like_count": 1, "type": 0}, {"created_at": 1537875709, "text": "Ada yang manggil2, ternyata yang dipanggil Robert yang lain... hahahaha", "user_id": 1548678158, "status": "Active", "bit_flags": 0, "content_type": "comment", "inline_composer_display_condition": "never", "has_liked_comment": false, "created_at_utc": 1537875709, "user": {"is_verified": false, "pk": 1548678158, "username": "lozhongting", "is_private": false, "profile_pic_id": "1739191320076112840_1548678158", "full_name": "LZT - Robert Gunadi", "profile_pic_url": "https://scontent-sit4-1.cdninstagram.com/vp/8e685671b6b0f401ded6839f88e1dd06/5C3FE5B5/t51.2885-19/s150x150/29091071_293801164484282_8630317274676330496_n.jpg"}, "pk": 17983434685046035, "did_report_as_spam": false, "comment_like_count": 0, "type": 0}, {"created_at": 1537875093, "text": "Awesome vibes!\ud83d\udd25\ud83d\udc4d", "user_id": 2034165965, "status": "Active", "bit_flags": 0, "content_type": "comment", "inline_composer_display_condition": "never", "has_liked_comment": false, "created_at_utc": 1537875093, "user": {"is_verified": false, "pk": 2034165965, "username": "vrkvngel", "latest_reel_media": 1539592892, "is_private": false, "profile_pic_id": "1884896496077697435_2034165965", "full_name": "L\u039e\u039f\u039d\u039bRD", "profile_pic_url": "https://scontent-sit4-1.cdninstagram.com/vp/2e824804dc8e845cca5d2ad38d5f695f/5C5ED10D/t51.2885-19/s150x150/42759623_2257704781129928_8908186175370428416_n.jpg"}, "pk": 17982705217007932, "did_report_as_spam": false, "comment_like_count": 0, "type": 0}, {"created_at": 1537870541, "text": "\ud83d\ude0d\ud83d\ude0d koohhh @robetbet", "user_id": 4358524134, "status": "Active", "bit_flags": 0, "content_type": "comment", "inline_composer_display_condition": "never", "has_liked_comment": false, "created_at_utc": 1537870541, "user": {"is_verified": false, "pk": 4358524134, "username": "yudizsari", "is_private": false, "profile_pic_id": "1823723934915628837_4358524134", "full_name": "sabar menanti mu \ud83d\ude18\ud83d\ude18\ud83d\ude18\ud83d\ude07\ud83d\ude07\ud83d\ude07", "profile_pic_url": "https://scontent-sit4-1.cdninstagram.com/vp/91d985ca0416b7a87528e7cf35d6084e/5C424FD7/t51.2885-19/s150x150/36671917_2154075531495511_5036544483995418624_n.jpg"}, "pk": 17966981887115158, "did_report_as_spam": false, "comment_like_count": 0, "type": 0}, {"created_at": 1537868376, "text": "ganteng bgt keren robet ih", "user_id": 5312860179, "status": "Active", "bit_flags": 0, "content_type": "comment", "inline_composer_display_condition": "never", "has_liked_comment": false, "created_at_utc": 1537868376, "user": {"is_verified": false, "pk": 5312860179, "username": "hendi10122", "is_private": true, "profile_pic_id": "1726942210669991627_5312860179", "full_name": "Suhendi", "profile_pic_url": "https://scontent-sit4-1.cdninstagram.com/vp/122dfee8f71deb8a112773dbe3c0c772/5C5ACCCA/t51.2885-19/s150x150/28434133_397124510752948_353872599014440960_n.jpg"}, "pk": 17969005162115279, "did_report_as_spam": false, "comment_like_count": 2, "type": 0}, {"created_at": 1537867656, "text": "The caption \ud83d\ude02", "user_id": 18520171, "status": "Active", "bit_flags": 0, "content_type": "comment", "inline_composer_display_condition": "never", "has_liked_comment": false, "created_at_utc": 1537867656, "user": {"is_verified": false, "pk": 18520171, "username": "evan_markus", "latest_reel_media": 1539625651, "is_private": false, "profile_pic_id": "1878174483355192906_18520171", "full_name": "Evan Mark", "profile_pic_url": "https://scontent-sit4-1.cdninstagram.com/vp/b119c3dd4db606de8d9365cf8f104710/5C5087CC/t51.2885-19/s150x150/41923864_1916769005296495_1034320629882421248_n.jpg"}, "pk": 17956248679130477, "did_report_as_spam": false, "comment_like_count": 1, "type": 0}], "user": "robetbet"}