{"user": "rivkychandra", "gender": "male", "age": "29", "comments": [{"user": {"is_verified": false, "pk": 692355920, "username": "millerwang_insomnia", "full_name": "MillerWang", "is_private": false, "profile_pic_url": "https://scontent-sin6-2.cdninstagram.com/vp/b1a462c34ba43fa442d4f46788f05a98/5C3D1B66/t51.2885-19/s150x150/12269992_1029373150447737_1543143129_a.jpg"}, "pk": 17879879977162645, "user_id": 692355920, "created_at": 1510301485, "has_liked_comment": false, "inline_composer_display_condition": "never", "created_at_utc": 1510301485, "comment_like_count": 0, "text": "\ud83d\ude04", "content_type": "comment", "type": 0, "did_report_as_spam": false, "bit_flags": 0, "status": "Active"}, {"user": {"is_verified": false, "pk": 464969857, "username": "reinard11", "full_name": "Reinard Pangestu", "is_private": false, "profile_pic_url": "https://scontent-sin6-2.cdninstagram.com/vp/4473bdec56384631a8a07515ba62c1f7/5C4B4268/t51.2885-19/s150x150/34768978_789447101245605_7222078660314923008_n.jpg", "profile_pic_id": "1803682800521755125_464969857"}, "pk": 17892700993066941, "user_id": 464969857, "created_at": 1505135015, "has_liked_comment": false, "inline_composer_display_condition": "never", "created_at_utc": 1505135015, "comment_like_count": 0, "text": "Besok ki", "content_type": "comment", "type": 0, "did_report_as_spam": false, "bit_flags": 0, "status": "Active"}, {"user": {"is_verified": false, "pk": 186795958, "username": "rianhugo", "full_name": "hugo.", "is_private": false, "profile_pic_url": "https://scontent-sin6-2.cdninstagram.com/vp/f2703d0cec040c75bfc7949a06872604/5C4CDF0C/t51.2885-19/s150x150/35364269_1649435508494219_2769996920846811136_n.jpg", "latest_reel_media": 1539621407, "profile_pic_id": "1807450809060663122_186795958"}, "pk": 17882486671081217, "user_id": 186795958, "created_at": 1505134002, "has_liked_comment": false, "inline_composer_display_condition": "never", "created_at_utc": 1505134002, "comment_like_count": 0, "text": "Aw", "content_type": "comment", "type": 0, "did_report_as_spam": false, "bit_flags": 0, "status": "Active"}, {"user": {"is_verified": false, "pk": 887545427, "username": "rivkychandra", "full_name": "Rivky Chandra", "is_private": false, "profile_pic_url": "https://scontent-sin6-2.cdninstagram.com/vp/4e5c543a30276968e691c471fd573c42/5C46E603/t51.2885-19/s150x150/41665177_289975435063046_2801174015434031104_n.jpg", "profile_pic_id": "1877791001218011164_887545427"}, "pk": 17872761211154551, "user_id": 887545427, "created_at": 1505132549, "has_liked_comment": false, "inline_composer_display_condition": "never", "created_at_utc": 1505132549, "comment_like_count": 0, "text": "@reinard11 \ud83d\ude12 udah itvw blom wkwkk", "content_type": "comment", "type": 0, "did_report_as_spam": false, "bit_flags": 0, "status": "Active"}, {"user": {"is_verified": false, "pk": 887545427, "username": "rivkychandra", "full_name": "Rivky Chandra", "is_private": false, "profile_pic_url": "https://scontent-sin6-2.cdninstagram.com/vp/4e5c543a30276968e691c471fd573c42/5C46E603/t51.2885-19/s150x150/41665177_289975435063046_2801174015434031104_n.jpg", "profile_pic_id": "1877791001218011164_887545427"}, "pk": 17898894046000038, "user_id": 887545427, "created_at": 1505132525, "has_liked_comment": false, "inline_composer_display_condition": "never", "created_at_utc": 1505132525, "comment_like_count": 0, "text": "@fennyhermanto ini kan karena kamera iphonemu mengalihkan wajah minyakku \ud83d\ude02", "content_type": "comment", "type": 0, "did_report_as_spam": false, "bit_flags": 0, "status": "Active"}, {"user": {"is_verified": false, "pk": 464969857, "username": "reinard11", "full_name": "Reinard Pangestu", "is_private": false, "profile_pic_url": "https://scontent-sin6-2.cdninstagram.com/vp/4473bdec56384631a8a07515ba62c1f7/5C4B4268/t51.2885-19/s150x150/34768978_789447101245605_7222078660314923008_n.jpg", "profile_pic_id": "1803682800521755125_464969857"}, "pk": 17886025687102617, "user_id": 464969857, "created_at": 1505131685, "has_liked_comment": false, "inline_composer_display_condition": "never", "created_at_utc": 1505131685, "comment_like_count": 0, "text": "Aw", "content_type": "comment", "type": 0, "did_report_as_spam": false, "bit_flags": 0, "status": "Active"}, {"user": {"is_verified": false, "pk": 202205543, "username": "fennyhermanto", "full_name": "Fenny Hermanto", "is_private": false, "profile_pic_url": "https://scontent-sin6-2.cdninstagram.com/vp/6d73112901ef4727d437a35cb6fc34f1/5C5EE355/t51.2885-19/s150x150/41514208_512265245903478_742034636372180992_n.jpg", "latest_reel_media": 1539617168, "profile_pic_id": "1872436137923263156_202205543"}, "pk": 17900661685024624, "user_id": 202205543, "created_at": 1505131303, "has_liked_comment": false, "inline_composer_display_condition": "never", "created_at_utc": 1505131303, "comment_like_count": 0, "text": "a en je ay \ud83d\udd25\u26a1\ufe0f", "content_type": "comment", "type": 0, "did_report_as_spam": false, "bit_flags": 0, "status": "Active"}]}