{"gender": "female", "user": "dzvigie", "comments": [{"text": "\u2764\ufe0f\u2764\ufe0f\u2764\ufe0f\u2764\ufe0f\u2764\ufe0f", "comment_like_count": 0, "bit_flags": 0, "created_at": 1539511943, "pk": 17991082918049407, "inline_composer_display_condition": "never", "status": "Active", "created_at_utc": 1539511943, "content_type": "comment", "has_liked_comment": false, "user": {"profile_pic_url": "https://scontent-sit4-1.cdninstagram.com/vp/98bb63b2d0d401ea44093c6d49d6b91e/5C4A6455/t51.2885-19/s150x150/35509319_2130014690568721_5757890765413941248_n.jpg", "latest_reel_media": 1539612832, "profile_pic_id": "1813828208800249313_1147942727", "full_name": "Syifa \u2022\ud83d\udccdSurabaya", "is_verified": false, "is_private": false, "username": "lillasyifa", "pk": 1147942727}, "user_id": 1147942727, "type": 0, "did_report_as_spam": false}, {"text": "Too pretty \ud83d\ude0d", "comment_like_count": 0, "bit_flags": 0, "created_at": 1539493882, "pk": 17966870590087337, "inline_composer_display_condition": "never", "status": "Active", "created_at_utc": 1539493882, "content_type": "comment", "has_liked_comment": false, "user": {"profile_pic_url": "https://scontent-sit4-1.cdninstagram.com/vp/34d4ccdebebc7e62de1ca74c62b8af8b/5C46AEBB/t51.2885-19/s150x150/25021945_1996777387202079_6576432534698065920_n.jpg", "latest_reel_media": 1539606181, "profile_pic_id": "1677015124228856320_311854635", "full_name": "Sisilia Dsi Maria S.S", "is_verified": false, "is_private": false, "username": "sisilia_dsi", "pk": 311854635}, "user_id": 311854635, "type": 0, "did_report_as_spam": false}, {"text": "Cantik banget, Deslin! \ud83c\udf38\ud83c\udf38\ud83c\udf38\nThank you for sharing the beauty pic! \u2764\ufe0f\u2764\ufe0f\u2764\ufe0f", "comment_like_count": 0, "bit_flags": 0, "created_at": 1539492068, "pk": 17878986538300341, "inline_composer_display_condition": "never", "status": "Active", "created_at_utc": 1539492068, "content_type": "comment", "has_liked_comment": false, "user": {"profile_pic_url": "https://scontent-sit4-1.cdninstagram.com/vp/ffdbebd196009a1bdb176d494712c2eb/5C45B45B/t51.2885-19/s150x150/32080795_1752505301495343_1757843703805771776_n.jpg", "latest_reel_media": 1539612167, "profile_pic_id": "1784832258624996499_5352979671", "full_name": "Lash \u2022 Nail \u2022 Wax", "is_verified": false, "is_private": false, "username": "yeolastudio", "pk": 5352979671}, "user_id": 5352979671, "type": 0, "did_report_as_spam": false}, {"text": "Hi beauty!\ud83d\ude18", "comment_like_count": 0, "bit_flags": 0, "created_at": 1539488755, "pk": 17871063658284740, "inline_composer_display_condition": "never", "status": "Active", "created_at_utc": 1539488755, "content_type": "comment", "has_liked_comment": false, "user": {"profile_pic_url": "https://scontent-sit4-1.cdninstagram.com/vp/2aeceb57f16230e886a866d191d6b6a3/5C4690DE/t51.2885-19/s150x150/43778675_2133961620204877_8956242839323279360_n.jpg", "latest_reel_media": 1539602553, "profile_pic_id": "1889778884129604536_486914298", "full_name": "MELLINDA EKY PUTRI", "is_verified": false, "is_private": false, "username": "mellindaep", "pk": 486914298}, "user_id": 486914298, "type": 0, "did_report_as_spam": false}, {"text": "Very beautiful \ud83c\udf39\ud83d\ude0d", "comment_like_count": 0, "bit_flags": 0, "created_at": 1539481024, "pk": 17889880060269083, "inline_composer_display_condition": "never", "status": "Active", "created_at_utc": 1539481024, "content_type": "comment", "has_liked_comment": false, "user": {"profile_pic_url": "https://scontent-sit4-1.cdninstagram.com/vp/55d7909722f52d587387e588dbf0ede3/5C4D59F4/t51.2885-19/s150x150/20904883_1397857200269600_4473782057436184576_a.jpg", "profile_pic_id": "1583393511381590495_1908550887", "full_name": "rudy", "is_verified": false, "is_private": true, "username": "rudyvindiesel", "pk": 1908550887}, "user_id": 1908550887, "type": 0, "did_report_as_spam": false}, {"text": "Haloo kak @dzvigie \ud83d\ude0a Aku mau kenalin produk yg lagi booming dan keren abis nih kak \ud83d\ude06\ud83d\ude06 Produknya itu Optrimax plum & Optrimax jelly, duo optrimax ini bagus banget di konsumsi kalo kk pengen nurunin berat badan, melancarkan BAB, suka jajan tapi ga mau gendut. Utk info lebih lanjut bisa langsung DM dan kepoin IG kita ya kak \ud83d\ude18\ud83d\ude18 @plumxjelly18", "comment_like_count": 1, "bit_flags": 0, "created_at": 1539476130, "pk": 17961630415184641, "inline_composer_display_condition": "never", "status": "Active", "created_at_utc": 1539476130, "content_type": "comment", "has_liked_comment": false, "user": {"profile_pic_url": "https://scontent-sit4-1.cdninstagram.com/vp/c8220ada48a78d1ca3a42a3f1df9e25e/5C56A096/t51.2885-19/s150x150/41763522_750737008591510_6913076465110089728_n.jpg", "latest_reel_media": 1539607729, "profile_pic_id": "1869335695362224497_8368573940", "full_name": "AWKARIN OPTRIMAX TRUSTED", "is_verified": false, "is_private": false, "username": "plumxjelly18", "pk": 8368573940}, "user_id": 8368573940, "type": 0, "did_report_as_spam": false}, {"text": "Cantik bgt cc \ud83d\ude0d\ud83d\ude0d\ud83d\ude0d\ud83d\udd25", "comment_like_count": 0, "bit_flags": 0, "created_at": 1539450482, "pk": 17929162531202411, "inline_composer_display_condition": "never", "status": "Active", "created_at_utc": 1539450482, "content_type": "comment", "has_liked_comment": false, "user": {"profile_pic_url": "https://scontent-sit4-1.cdninstagram.com/vp/5c0ca35f8333fc57cbcf57ff1bcfcad1/5C5ED42B/t51.2885-19/s150x150/41248858_952963581554231_4949893819446329344_n.jpg", "profile_pic_id": "1874504145826976117_1202158667", "full_name": "Kirstenzia Ivena Helda", "is_verified": false, "is_private": false, "username": "ivenahelda", "pk": 1202158667}, "user_id": 1202158667, "type": 0, "did_report_as_spam": false}, {"text": "\ud83d\ude0d\ud83d\ude0d\ud83d\ude0d\ud83d\ude0d\ud83d\ude0d", "comment_like_count": 0, "bit_flags": 0, "created_at": 1539449803, "pk": 17988961183057096, "inline_composer_display_condition": "never", "status": "Active", "created_at_utc": 1539449803, "content_type": "comment", "has_liked_comment": false, "user": {"profile_pic_url": "https://scontent-sit4-1.cdninstagram.com/vp/069be0a9c99e40ddc7bbf29a9f4ffc72/5C5046C0/t51.2885-19/s150x150/42475704_2163664983676589_2978508104074788864_n.jpg", "profile_pic_id": "1889386509398459116_300492052", "full_name": "\ud835\udc45\ud835\udcb6\ud835\udcb8\ud835\udcbd\ud835\udc52\ud835\udcc1 \ud835\udc9e\ud835\udcb6\ud835\udcc7\ud835\udc5c\ud835\udcc1\ud835\udcbe\ud835\udcc3\ud835\udc52 \ud835\udcab\ud835\udcb6\ud835\udcc3\ud835\udc54\ud835\udc52\ud835\udcc2\ud835\udcb6\ud835\udcc3\ud835\udcb6\ud835\udcc3", "is_verified": false, "is_private": false, "username": "rachvy", "pk": 300492052}, "user_id": 300492052, "type": 0, "did_report_as_spam": false}, {"text": "Waduh cantikk benarr", "comment_like_count": 0, "bit_flags": 0, "created_at": 1539448144, "pk": 17870619283304494, "inline_composer_display_condition": "never", "status": "Active", "created_at_utc": 1539448144, "content_type": "comment", "has_liked_comment": false, "user": {"profile_pic_url": "https://scontent-sit4-1.cdninstagram.com/vp/af2773b297bdae1a170e00f84bacbc3c/5C58E86C/t51.2885-19/s150x150/32817547_393912957753051_3322797106338463744_n.jpg", "profile_pic_id": "1792198000661377857_7813659237", "full_name": "athok", "is_verified": false, "is_private": false, "username": "athok8", "pk": 7813659237}, "user_id": 7813659237, "type": 0, "did_report_as_spam": false}, {"text": "\ud83d\udc9b\ud83d\udc9b\ud83d\udc9b\ud83d\udc9b\ud83d\udc9b\ud83d\udc9b\ud83d\udc9b\ud83d\udc9b", "comment_like_count": 0, "bit_flags": 0, "created_at": 1539447083, "pk": 17989705339021384, "inline_composer_display_condition": "never", "status": "Active", "created_at_utc": 1539447083, "content_type": "comment", "has_liked_comment": false, "user": {"profile_pic_url": "https://scontent-sit4-1.cdninstagram.com/vp/757906227191562707b7b6fc6c073f61/5C55EA3D/t51.2885-19/s150x150/22352034_1311143165680590_2811612194712584192_n.jpg", "latest_reel_media": 1539606931, "profile_pic_id": "1622791505402233069_236619336", "full_name": "Anggita Mega Mentari", "is_verified": false, "is_private": false, "username": "megamentarim", "pk": 236619336}, "user_id": 236619336, "type": 0, "did_report_as_spam": false}, {"text": "Hepi wikend Cantik \ud83d\udc83\ud83c\udffb", "comment_like_count": 0, "bit_flags": 0, "created_at": 1539445185, "pk": 17911119583245834, "inline_composer_display_condition": "never", "status": "Active", "created_at_utc": 1539445185, "content_type": "comment", "has_liked_comment": false, "user": {"profile_pic_url": "https://scontent-sit4-1.cdninstagram.com/vp/cbcf54d1ea9d6ad884d558b97cfd8daf/5C4F59D4/t51.2885-19/s150x150/42353559_769055643426670_729833970019074048_n.jpg", "latest_reel_media": 1539615193, "profile_pic_id": "1888722354344575227_712984793", "full_name": "V \u0118 R O N", "is_verified": false, "is_private": false, "username": "ve.veron", "pk": 712984793}, "user_id": 712984793, "type": 0, "did_report_as_spam": false}, {"text": "\u3297\ufe0f\u3297\ufe0f\u3297\ufe0f\u3297\ufe0f\u3297\ufe0f\u3297\ufe0fA\u53d8B\u25b6\ufe0fC\u53d8D\u25b6\ufe0fC\u53d8D\ud83c\udd9a\ud83c\udd9a\ud83c\udd9a\ud83d\udc83\ud83d\udc83\ud83d\udc83\ud83d\udc83\ud83d\udc83\ud83d\udc83\ud83d\udc83\ud83d\udc83\ud83d\udc83\u524d\u9762\u633a\u8d77\u6765\uff0c\u540e\u9762\u7fd8\u8d77\u6765\ud83d\udc83\ud83d\udc83\ud83d\udc83\ud83d\udc83\u5b8c\u7f8e\u642d\u914d\ud83d\udc83\ud83d\udc83", "comment_like_count": 0, "bit_flags": 0, "created_at": 1539444028, "pk": 17989113961063631, "inline_composer_display_condition": "never", "status": "Active", "created_at_utc": 1539444028, "content_type": "comment", "has_liked_comment": false, "user": {"profile_pic_url": "https://scontent-sit4-1.cdninstagram.com/vp/7d05af054a297dd029728133467cee31/5C4A8294/t51.2885-19/s150x150/42593422_932731833585900_4475589070436696064_n.jpg", "profile_pic_id": "1813908503036006477_1960612514", "full_name": "\u4e2d\u836f\u51cf\u80a5\u2764\ufe0f\u4e30\u80f8\u2764\ufe0f\u7f29\u9634\u2764\ufe0f\u7f8e\u767d\u818f", "is_verified": false, "is_private": false, "username": "jie00142", "pk": 1960612514}, "user_id": 1960612514, "type": 0, "did_report_as_spam": false}, {"text": "XD \nwaiting for uuuuuu\n\u5feb\u6765\u70b9\u6211\uff01", "comment_like_count": 0, "bit_flags": 0, "created_at": 1539443150, "pk": 17967038020083519, "inline_composer_display_condition": "never", "status": "Active", "created_at_utc": 1539443150, "content_type": "comment", "has_liked_comment": false, "user": {"profile_pic_url": "https://scontent-sit4-1.cdninstagram.com/vp/c69c5255b7bd8c77c62bb94a8b78d3b1/5C6264A6/t51.2885-19/s150x150/31033903_462574490863379_9062913437360717824_n.jpg", "profile_pic_id": "1778191466210731924_7736046326", "full_name": "\u4e94\u5e74\u8001\u53f7\u88ab\u5c01\ud83d\ude14\u65b0\u4e3b\u53f7@ayystudios", "is_verified": false, "is_private": false, "username": "ayystudio40", "pk": 7736046326}, "user_id": 7736046326, "type": 0, "did_report_as_spam": false}, {"text": "\ud83d\ude0d\ud83d\ude0d", "comment_like_count": 0, "bit_flags": 0, "created_at": 1539440741, "pk": 17946445717194004, "inline_composer_display_condition": "never", "status": "Active", "created_at_utc": 1539440741, "content_type": "comment", "has_liked_comment": false, "user": {"profile_pic_url": "https://scontent-sit4-1.cdninstagram.com/vp/7ad1a6bd12ed967549c8a644c7f037bd/5C55A71C/t51.2885-19/s150x150/42521427_1876014349178405_5871820442297171968_n.jpg", "profile_pic_id": "1887904261314946868_2154673776", "full_name": "Hendy Kusuma", "is_verified": false, "is_private": false, "username": "hen_dykusuma", "pk": 2154673776}, "user_id": 2154673776, "type": 0, "did_report_as_spam": false}, {"text": "Kebangetan dah sadisnyaaaaaa", "comment_like_count": 0, "bit_flags": 0, "created_at": 1539437339, "pk": 17973757987128401, "inline_composer_display_condition": "never", "status": "Active", "created_at_utc": 1539437339, "content_type": "comment", "has_liked_comment": false, "user": {"profile_pic_url": "https://scontent-sit4-1.cdninstagram.com/vp/6f1c16c6e5c59939882eb92891ad24d4/5C4C9F3E/t51.2885-19/10598222_1523124711255584_50838980_a.jpg", "full_name": "Daphie Sagita", "is_verified": false, "is_private": true, "username": "daphie_sagita", "pk": 357041725}, "user_id": 357041725, "type": 0, "did_report_as_spam": false}, {"text": "\ud83d\ude0d\ud83d\ude0d", "comment_like_count": 0, "bit_flags": 0, "created_at": 1539435533, "pk": 17979397060076003, "inline_composer_display_condition": "never", "status": "Active", "created_at_utc": 1539435533, "content_type": "comment", "has_liked_comment": false, "user": {"profile_pic_url": "https://scontent-sit4-1.cdninstagram.com/vp/304f1f0502ab61f4d1068ea4bba21eec/5C4279F0/t51.2885-19/s150x150/42082104_502246320185925_5207425676331712512_n.jpg", "latest_reel_media": 1539580143, "profile_pic_id": "1879505761114379250_1831254846", "full_name": "valencia winata\ud83d\udc23", "is_verified": false, "is_private": false, "username": "valenciawinataa", "pk": 1831254846}, "user_id": 1831254846, "type": 0, "did_report_as_spam": false}, {"text": "\ud83d\ude0d", "comment_like_count": 0, "bit_flags": 0, "created_at": 1539435463, "pk": 17964935413138467, "inline_composer_display_condition": "never", "status": "Active", "created_at_utc": 1539435463, "content_type": "comment", "has_liked_comment": false, "user": {"profile_pic_url": "https://scontent-sit4-1.cdninstagram.com/vp/9c4a36d5318b213f519caf32688c9af8/5C4C40C0/t51.2885-19/s150x150/40501856_1853429214748685_2620784839246217216_n.jpg", "profile_pic_id": "1879593440884736123_696768219", "full_name": "Wilya Carlina\ud83c\udf3b", "is_verified": false, "is_private": false, "username": "wilyalam", "pk": 696768219}, "user_id": 696768219, "type": 0, "did_report_as_spam": false}, {"text": "Omg keren dessss \ud83d\ude0d\ud83d\ude0d", "comment_like_count": 0, "bit_flags": 0, "created_at": 1539609610, "pk": 17974311589101167, "inline_composer_display_condition": "never", "status": "Active", "created_at_utc": 1539609610, "content_type": "comment", "has_liked_comment": false, "user": {"profile_pic_url": "https://scontent-sit4-1.cdninstagram.com/vp/d5126efdc7ac7289875e3ed156ef7aca/5C3BD186/t51.2885-19/s150x150/42450848_715848245440391_4761042170410958848_n.jpg", "latest_reel_media": 1539599570, "profile_pic_id": "1888599415888232015_243209056", "full_name": "CITRA OLIVIA ONG \u2661", "is_verified": false, "is_private": false, "username": "citraolivia", "pk": 243209056}, "user_id": 243209056, "type": 0, "did_report_as_spam": false}, {"text": "\ud83d\ude0d\ud83d\ude0d\ud83d\udc96\ud83d\udc96", "comment_like_count": 0, "bit_flags": 0, "created_at": 1539315968, "pk": 17867021092285021, "inline_composer_display_condition": "never", "status": "Active", "created_at_utc": 1539315968, "content_type": "comment", "has_liked_comment": false, "user": {"profile_pic_url": "https://scontent-sit4-1.cdninstagram.com/vp/417aa84a54c5d8af3270c87fb53b537b/5C5C1ED0/t51.2885-19/s150x150/37807838_278677442724696_7557042949276565504_n.jpg", "latest_reel_media": 1539607941, "profile_pic_id": "1840604325275907297_233958008", "full_name": "Monica Adhelia", "is_verified": false, "is_private": false, "username": "monicaadheliaa", "pk": 233958008}, "user_id": 233958008, "type": 0, "did_report_as_spam": false}, {"text": "Pretty cool sis deslin\ud83d\ude0dNew arrival \ud83d\udd25 baru khusus harga TERMURAH se instagram sudah d upload sis, segera borong ke @foxybabe_clothing \ud83d\ude31\u2764\ufe0f", "comment_like_count": 0, "bit_flags": 0, "created_at": 1539313360, "pk": 17914999720236949, "inline_composer_display_condition": "never", "status": "Active", "created_at_utc": 1539313360, "content_type": "comment", "has_liked_comment": false, "user": {"profile_pic_url": "https://scontent-sit4-1.cdninstagram.com/vp/019e021f2c17e94c6035d1552c0d3a59/5C3EAD26/t51.2885-19/s150x150/16585271_1245741605515602_3968849634645770240_a.jpg", "latest_reel_media": 1539578276, "profile_pic_id": "1450054136616123618_1919608041", "full_name": "SUPPLIER AUTHENTIC FASHION", "is_verified": false, "is_private": false, "username": "foxybabe_clothing", "pk": 1919608041}, "user_id": 1919608041, "type": 0, "did_report_as_spam": false}, {"text": "\ud83d\ude0d\ud83d\ude0d", "comment_like_count": 0, "bit_flags": 0, "created_at": 1539274369, "pk": 17955265165162388, "inline_composer_display_condition": "never", "status": "Active", "created_at_utc": 1539274369, "content_type": "comment", "has_liked_comment": false, "user": {"profile_pic_url": "https://scontent-sit4-1.cdninstagram.com/vp/cbcf54d1ea9d6ad884d558b97cfd8daf/5C4F59D4/t51.2885-19/s150x150/42353559_769055643426670_729833970019074048_n.jpg", "latest_reel_media": 1539615193, "profile_pic_id": "1888722354344575227_712984793", "full_name": "V \u0118 R O N", "is_verified": false, "is_private": false, "username": "ve.veron", "pk": 712984793}, "user_id": 712984793, "type": 0, "did_report_as_spam": false}, {"text": "\u673a\u667a\u7684\u4f60\u4e00\u5b9a\u61c2(\u0e51\u02c3\u0335\u1d17\u02c2\u0335)\u0648 \u6700\u7f8e\u7684\u4f60 waitng for u\u0b18(\u0a6d\u02ca\ua4b3 \u02cb)\u0a6d\u2727", "comment_like_count": 0, "bit_flags": 0, "created_at": 1539273058, "pk": 17986874227011407, "inline_composer_display_condition": "never", "status": "Active", "created_at_utc": 1539273058, "content_type": "comment", "has_liked_comment": false, "user": {"profile_pic_url": "https://scontent-sit4-1.cdninstagram.com/vp/c69c5255b7bd8c77c62bb94a8b78d3b1/5C6264A6/t51.2885-19/s150x150/31033903_462574490863379_9062913437360717824_n.jpg", "profile_pic_id": "1778191466210731924_7736046326", "full_name": "\u4e94\u5e74\u8001\u53f7\u88ab\u5c01\ud83d\ude14\u65b0\u4e3b\u53f7@ayystudios", "is_verified": false, "is_private": false, "username": "ayystudio40", "pk": 7736046326}, "user_id": 7736046326, "type": 0, "did_report_as_spam": false}, {"text": "Very beautiful", "comment_like_count": 0, "bit_flags": 0, "created_at": 1539262063, "pk": 17961409906187060, "inline_composer_display_condition": "never", "status": "Active", "created_at_utc": 1539262063, "content_type": "comment", "has_liked_comment": false, "user": {"profile_pic_url": "https://scontent-sit4-1.cdninstagram.com/vp/55d7909722f52d587387e588dbf0ede3/5C4D59F4/t51.2885-19/s150x150/20904883_1397857200269600_4473782057436184576_a.jpg", "profile_pic_id": "1583393511381590495_1908550887", "full_name": "rudy", "is_verified": false, "is_private": true, "username": "rudyvindiesel", "pk": 1908550887}, "user_id": 1908550887, "type": 0, "did_report_as_spam": false}, {"text": "Suka Ekspresinya \ud83d\ude0d", "comment_like_count": 0, "bit_flags": 0, "created_at": 1539261124, "pk": 17986722325051184, "inline_composer_display_condition": "never", "status": "Active", "created_at_utc": 1539261124, "content_type": "comment", "has_liked_comment": false, "user": {"profile_pic_url": "https://scontent-sit4-1.cdninstagram.com/vp/6f1c16c6e5c59939882eb92891ad24d4/5C4C9F3E/t51.2885-19/10598222_1523124711255584_50838980_a.jpg", "full_name": "Daphie Sagita", "is_verified": false, "is_private": true, "username": "daphie_sagita", "pk": 357041725}, "user_id": 357041725, "type": 0, "did_report_as_spam": false}, {"text": "Woww\ud83d\udd25", "comment_like_count": 1, "bit_flags": 0, "created_at": 1539260483, "pk": 17990043922054928, "inline_composer_display_condition": "never", "status": "Active", "created_at_utc": 1539260483, "content_type": "comment", "has_liked_comment": false, "user": {"profile_pic_url": "https://scontent-sit4-1.cdninstagram.com/vp/ac25f1e2e43f88d3428a86d3bf43af6f/5C512747/t51.2885-19/s150x150/42308235_2245421015470515_8985242810693189632_n.jpg", "latest_reel_media": 1539616358, "profile_pic_id": "1887859382201596436_216712338", "full_name": "Annita Liem \u264c", "is_verified": false, "is_private": false, "username": "annita_iap", "pk": 216712338}, "user_id": 216712338, "type": 0, "did_report_as_spam": false}, {"text": "\ud83d\udc97\ud83d\udc97\ud83d\udc97", "comment_like_count": 0, "bit_flags": 0, "created_at": 1539259993, "pk": 17924291089222810, "inline_composer_display_condition": "never", "status": "Active", "created_at_utc": 1539259993, "content_type": "comment", "has_liked_comment": false, "user": {"profile_pic_url": "https://scontent-sit4-1.cdninstagram.com/vp/6dcf05c7b2cbe78222f699a97307dd24/5C4B5360/t51.2885-19/s150x150/36113477_224288998186757_37119276330516480_n.jpg", "latest_reel_media": 1539604056, "profile_pic_id": "1817594547702765441_306667294", "full_name": "Xiu Ling \ud83c\udf19", "is_verified": false, "is_private": false, "username": "dianaxiuling", "pk": 306667294}, "user_id": 306667294, "type": 0, "did_report_as_spam": false}, {"text": "\ud83d\udda4\ud83d\udda4", "comment_like_count": 0, "bit_flags": 0, "created_at": 1539259768, "pk": 17945092561199872, "inline_composer_display_condition": "never", "status": "Active", "created_at_utc": 1539259768, "content_type": "comment", "has_liked_comment": false, "user": {"profile_pic_url": "https://scontent-sit4-1.cdninstagram.com/vp/bde2b5c113ae371381db55c531811420/5C439D75/t51.2885-19/s150x150/35166367_1771903949571330_4519911359109922816_n.jpg", "profile_pic_id": "1814676783608199221_353006896", "full_name": "Jessica O. Indrawan \u221e", "is_verified": false, "is_private": false, "username": "jesszoctavia", "pk": 353006896}, "user_id": 353006896, "type": 0, "did_report_as_spam": false}, {"text": "Cantik \ud83d\ude0d", "comment_like_count": 0, "bit_flags": 0, "created_at": 1539259359, "pk": 17974479955102539, "inline_composer_display_condition": "never", "status": "Active", "created_at_utc": 1539259359, "content_type": "comment", "has_liked_comment": false, "user": {"profile_pic_url": "https://scontent-sit4-1.cdninstagram.com/vp/cd8b0535a4f04ebc119e8bcaa69da824/5C493A8D/t51.2885-19/s150x150/32307799_197905477498136_6380179956932018176_n.jpg", "latest_reel_media": 1539603278, "profile_pic_id": "1786625579254421140_3440369418", "full_name": "Grey", "is_verified": false, "is_private": false, "username": "thania_grey", "pk": 3440369418}, "user_id": 3440369418, "type": 0, "did_report_as_spam": false}, {"text": "Nice babe", "comment_like_count": 0, "bit_flags": 0, "created_at": 1539258671, "pk": 17988091996032771, "inline_composer_display_condition": "never", "status": "Active", "created_at_utc": 1539258671, "content_type": "comment", "has_liked_comment": false, "user": {"profile_pic_url": "https://scontent-sit4-1.cdninstagram.com/vp/1ebdf44fadfc63a208747fbe2727291d/5C5CA3B6/t51.2885-19/s150x150/42305758_291959151408413_3345755033680478208_n.jpg", "latest_reel_media": 1539577748, "profile_pic_id": "1887875450194569858_2234851869", "full_name": "Adinda Ester M. S. Simanjuntak", "is_verified": false, "is_private": false, "username": "adindaesterm", "pk": 2234851869}, "user_id": 2234851869, "type": 0, "did_report_as_spam": false}, {"text": "Aaahh cantik\ud83d\ude0d", "comment_like_count": 0, "bit_flags": 0, "created_at": 1539255924, "pk": 17970400807124932, "inline_composer_display_condition": "never", "status": "Active", "created_at_utc": 1539255924, "content_type": "comment", "has_liked_comment": false, "user": {"profile_pic_url": "https://scontent-sit4-1.cdninstagram.com/vp/cd8b0535a4f04ebc119e8bcaa69da824/5C493A8D/t51.2885-19/s150x150/32307799_197905477498136_6380179956932018176_n.jpg", "latest_reel_media": 1539603278, "profile_pic_id": "1786625579254421140_3440369418", "full_name": "Grey", "is_verified": false, "is_private": false, "username": "thania_grey", "pk": 3440369418}, "user_id": 3440369418, "type": 0, "did_report_as_spam": false}, {"text": "Nice \ud83d\ude0d\ud83d\ude0d", "comment_like_count": 0, "bit_flags": 0, "created_at": 1539248816, "pk": 17987824315039023, "inline_composer_display_condition": "never", "status": "Active", "created_at_utc": 1539248816, "content_type": "comment", "has_liked_comment": false, "user": {"profile_pic_url": "https://scontent-sit4-1.cdninstagram.com/vp/4d76ec97e00d1cdcd72a451cc3d5d467/5C62F05F/t51.2885-19/s150x150/42144783_2009011765785958_2134525731667968000_n.jpg", "profile_pic_id": "1879488872975746525_8378843954", "full_name": "C1ndy99", "is_verified": false, "is_private": true, "username": "_c1ndy99", "pk": 8378843954}, "user_id": 8378843954, "type": 0, "did_report_as_spam": false}, {"text": "Absolutely Gorjes \u2728", "comment_like_count": 0, "bit_flags": 0, "created_at": 1539238980, "pk": 17896227184256916, "inline_composer_display_condition": "never", "status": "Active", "created_at_utc": 1539238980, "content_type": "comment", "has_liked_comment": false, "user": {"profile_pic_url": "https://scontent-sit4-1.cdninstagram.com/vp/cbcf54d1ea9d6ad884d558b97cfd8daf/5C4F59D4/t51.2885-19/s150x150/42353559_769055643426670_729833970019074048_n.jpg", "latest_reel_media": 1539615193, "profile_pic_id": "1888722354344575227_712984793", "full_name": "V \u0118 R O N", "is_verified": false, "is_private": false, "username": "ve.veron", "pk": 712984793}, "user_id": 712984793, "type": 0, "did_report_as_spam": false}, {"text": "Duh cantiknyaaa", "comment_like_count": 0, "bit_flags": 0, "created_at": 1539233770, "pk": 17988859486013686, "inline_composer_display_condition": "never", "status": "Active", "created_at_utc": 1539233770, "content_type": "comment", "has_liked_comment": false, "user": {"profile_pic_url": "https://scontent-sit4-1.cdninstagram.com/vp/34d4ccdebebc7e62de1ca74c62b8af8b/5C46AEBB/t51.2885-19/s150x150/25021945_1996777387202079_6576432534698065920_n.jpg", "latest_reel_media": 1539606181, "profile_pic_id": "1677015124228856320_311854635", "full_name": "Sisilia Dsi Maria S.S", "is_verified": false, "is_private": false, "username": "sisilia_dsi", "pk": 311854635}, "user_id": 311854635, "type": 0, "did_report_as_spam": false}, {"text": "Komen dikit, bagus sih putih gt background lu, tapi lu kurang maju dikit, kalo lu nempel gt kurang bagus", "comment_like_count": 0, "bit_flags": 0, "created_at": 1539232237, "pk": 17966707090081229, "inline_composer_display_condition": "never", "status": "Active", "created_at_utc": 1539232237, "content_type": "comment", "has_liked_comment": false, "user": {"profile_pic_url": "https://scontent-sit4-1.cdninstagram.com/vp/22f11ff8822f21d773889e7c060777bc/5C44FEE7/t51.2885-19/s150x150/21985357_1307903489318191_484501306313015296_n.jpg", "profile_pic_id": "1441775134141693016_4561912227", "full_name": "Taufiq Aditomo Pasharibu", "is_verified": false, "is_private": false, "username": "taufiq_adit1", "pk": 4561912227}, "user_id": 4561912227, "type": 0, "did_report_as_spam": false}, {"text": "Cantik sekali sis deslin\ud83d\ude0dNew arrival \ud83d\udd25 baru khusus harga TERMURAH se instagram sudah d upload sis, segera borong ke @foxybabe_clothing \ud83d\ude31\u2764\ufe0f", "comment_like_count": 0, "bit_flags": 0, "created_at": 1539225791, "pk": 17957741155158046, "inline_composer_display_condition": "never", "status": "Active", "created_at_utc": 1539225791, "content_type": "comment", "has_liked_comment": false, "user": {"profile_pic_url": "https://scontent-sit4-1.cdninstagram.com/vp/019e021f2c17e94c6035d1552c0d3a59/5C3EAD26/t51.2885-19/s150x150/16585271_1245741605515602_3968849634645770240_a.jpg", "latest_reel_media": 1539578276, "profile_pic_id": "1450054136616123618_1919608041", "full_name": "SUPPLIER AUTHENTIC FASHION", "is_verified": false, "is_private": false, "username": "foxybabe_clothing", "pk": 1919608041}, "user_id": 1919608041, "type": 0, "did_report_as_spam": false}, {"text": "Bagus ya video nya", "comment_like_count": 1, "bit_flags": 0, "created_at": 1539190540, "pk": 17973106789108486, "inline_composer_display_condition": "never", "status": "Active", "created_at_utc": 1539190540, "content_type": "comment", "has_liked_comment": false, "user": {"profile_pic_url": "https://scontent-sit4-1.cdninstagram.com/vp/da26d546e8ded81e06e99efaab6855a6/5C50AFED/t51.2885-19/s150x150/19622846_1605847622759816_1682622265058918400_a.jpg", "latest_reel_media": 1539618457, "profile_pic_id": "1551581794271323623_31966793", "full_name": "Grace Juventia", "is_verified": false, "is_private": false, "username": "eugenia_grace", "pk": 31966793}, "user_id": 31966793, "type": 0, "did_report_as_spam": false}, {"text": "\u2728\u2728\u2728\u2728", "comment_like_count": 0, "bit_flags": 0, "created_at": 1539190054, "pk": 17895873022262086, "inline_composer_display_condition": "never", "status": "Active", "created_at_utc": 1539190054, "content_type": "comment", "has_liked_comment": false, "user": {"profile_pic_url": "https://scontent-sit4-1.cdninstagram.com/vp/cee887d213ab2024e859ec73fe194c6a/5C3DC239/t51.2885-19/s150x150/41529847_276660842976316_8944626563400335360_n.jpg", "profile_pic_id": "1877401955060753596_219666798", "full_name": "\ud835\udd38\ud835\udd57\ud835\udd5a\ud835\udd57", "is_verified": false, "is_private": false, "username": "kuloafif", "pk": 219666798}, "user_id": 219666798, "type": 0, "did_report_as_spam": false}, {"text": "\u6211\u8fd8\u662f\u5728\u8fd9\u91cc \u0e05\u0295\u2022\u032b\u0361\u2022\u0294\u0e05 \u0e05\u0295\u2022\u032b\u0361\u2022\u0294\u0e05", "comment_like_count": 0, "bit_flags": 0, "created_at": 1539188288, "pk": 17966262196087324, "inline_composer_display_condition": "never", "status": "Active", "created_at_utc": 1539188288, "content_type": "comment", "has_liked_comment": false, "user": {"profile_pic_url": "https://scontent-sit4-1.cdninstagram.com/vp/c69c5255b7bd8c77c62bb94a8b78d3b1/5C6264A6/t51.2885-19/s150x150/31033903_462574490863379_9062913437360717824_n.jpg", "profile_pic_id": "1778191466210731924_7736046326", "full_name": "\u4e94\u5e74\u8001\u53f7\u88ab\u5c01\ud83d\ude14\u65b0\u4e3b\u53f7@ayystudios", "is_verified": false, "is_private": false, "username": "ayystudio40", "pk": 7736046326}, "user_id": 7736046326, "type": 0, "did_report_as_spam": false}, {"text": "@nancylaurencia ohhh jelassssss ..\ud83e\udd2a\ud83d\ude02\ud83d\ude02", "bit_flags": 0, "created_at": 1539182503, "pk": 17958318166182430, "inline_composer_display_condition": "never", "status": "Active", "created_at_utc": 1539182503, "content_type": "comment", "user": {"profile_pic_url": "https://scontent-sit4-1.cdninstagram.com/vp/54feef716228b1753da4d0f5dd74d077/5C47843F/t51.2885-19/s150x150/41870613_105268017071696_1905359698526208000_n.jpg", "latest_reel_media": 1539607278, "profile_pic_id": "1878835517468409821_10654483", "full_name": "Deslin Virgina", "is_verified": false, "is_private": false, "username": "dzvigie", "pk": 10654483}, "user_id": 10654483, "type": 2, "did_report_as_spam": false}, {"text": "Cantik banget\ud83d\ude0d", "comment_like_count": 0, "bit_flags": 0, "created_at": 1539181434, "pk": 17970226738123621, "inline_composer_display_condition": "never", "status": "Active", "created_at_utc": 1539181434, "content_type": "comment", "has_liked_comment": false, "user": {"profile_pic_url": "https://scontent-sit4-1.cdninstagram.com/vp/6b1467d6e16dfe6d5d7d2877866e598b/5C5C1E0B/t51.2885-19/s150x150/42003698_1824378650948969_3320063419784101888_n.jpg", "latest_reel_media": 1539597909, "profile_pic_id": "1879756228759307820_27205174", "full_name": "\ud83c\udf2cn a n c y l a u r e n c i a", "is_verified": false, "is_private": false, "username": "nancylaurencia", "pk": 27205174}, "user_id": 27205174, "type": 0, "did_report_as_spam": false}, {"text": "Very beautiful \ud83c\udf39", "comment_like_count": 0, "bit_flags": 0, "created_at": 1538272958, "pk": 17983608823007358, "inline_composer_display_condition": "never", "status": "Active", "created_at_utc": 1538272958, "content_type": "comment", "has_liked_comment": false, "user": {"profile_pic_url": "https://scontent-sit4-1.cdninstagram.com/vp/55d7909722f52d587387e588dbf0ede3/5C4D59F4/t51.2885-19/s150x150/20904883_1397857200269600_4473782057436184576_a.jpg", "profile_pic_id": "1583393511381590495_1908550887", "full_name": "rudy", "is_verified": false, "is_private": true, "username": "rudyvindiesel", "pk": 1908550887}, "user_id": 1908550887, "type": 0, "did_report_as_spam": false}, {"text": "\u6253\u4ec0\u4e48\u5e7f\u544a\u90fd\u88ab\u9650\u5236\n\u7b97\u4e86 \u611f\u5174\u8da3\u6233\u6211\u5c31\u597d\u0e05\u2022\u0300\u2200\u2022\u0301\u0e05", "comment_like_count": 0, "bit_flags": 0, "created_at": 1538264306, "pk": 17955229693150555, "inline_composer_display_condition": "never", "status": "Active", "created_at_utc": 1538264306, "content_type": "comment", "has_liked_comment": false, "user": {"profile_pic_url": "https://scontent-sit4-1.cdninstagram.com/vp/c69c5255b7bd8c77c62bb94a8b78d3b1/5C6264A6/t51.2885-19/s150x150/31033903_462574490863379_9062913437360717824_n.jpg", "profile_pic_id": "1778191466210731924_7736046326", "full_name": "\u4e94\u5e74\u8001\u53f7\u88ab\u5c01\ud83d\ude14\u65b0\u4e3b\u53f7@ayystudios", "is_verified": false, "is_private": false, "username": "ayystudio40", "pk": 7736046326}, "user_id": 7736046326, "type": 0, "did_report_as_spam": false}, {"text": "Hai kak follow @totomo.id yaa kita lagi ada promo dapetin potongan harga 50ribu  lohh \ud83d\ude0d\ud83d\ude0d", "comment_like_count": 0, "bit_flags": 0, "created_at": 1538259510, "pk": 17966212984121294, "inline_composer_display_condition": "never", "status": "Active", "created_at_utc": 1538259510, "content_type": "comment", "has_liked_comment": false, "user": {"profile_pic_url": "https://scontent-sit4-1.cdninstagram.com/vp/5785348f1f38bea57bdf9f31f6d30c64/5C4F63D2/t51.2885-19/s150x150/40893806_912374085640451_2864177144102125568_n.jpg", "profile_pic_id": "1869289503366419176_2089916476", "full_name": "TOTOMO.ID", "is_verified": false, "is_private": false, "username": "totomo.id", "pk": 2089916476}, "user_id": 2089916476, "type": 0, "did_report_as_spam": false}, {"text": "\ud83d\ude0d\ud83d\ude0d", "comment_like_count": 0, "bit_flags": 0, "created_at": 1538245803, "pk": 17853492253290856, "inline_composer_display_condition": "never", "status": "Active", "created_at_utc": 1538245803, "content_type": "comment", "has_liked_comment": false, "user": {"profile_pic_url": "https://scontent-sit4-1.cdninstagram.com/vp/ad6e172b6af2c9f3bc406402846ae5ff/5C477E41/t51.2885-19/s150x150/42570242_436406083431185_220990330965590016_n.jpg", "latest_reel_media": 1539615806, "profile_pic_id": "1890124637251306855_325343860", "full_name": "Evelyn Stevanie", "is_verified": false, "is_private": false, "username": "evelynstevanie", "pk": 325343860}, "user_id": 325343860, "type": 0, "did_report_as_spam": false}, {"text": "\u2728Happy Weekend Cantik\ud83d\udc83\ud83c\udffb", "comment_like_count": 0, "bit_flags": 0, "created_at": 1538229798, "pk": 17954944825149086, "inline_composer_display_condition": "never", "status": "Active", "created_at_utc": 1538229798, "content_type": "comment", "has_liked_comment": false, "user": {"profile_pic_url": "https://scontent-sit4-1.cdninstagram.com/vp/cbcf54d1ea9d6ad884d558b97cfd8daf/5C4F59D4/t51.2885-19/s150x150/42353559_769055643426670_729833970019074048_n.jpg", "latest_reel_media": 1539615193, "profile_pic_id": "1888722354344575227_712984793", "full_name": "V \u0118 R O N", "is_verified": false, "is_private": false, "username": "ve.veron", "pk": 712984793}, "user_id": 712984793, "type": 0, "did_report_as_spam": false}, {"text": "\ud83d\ude0d", "comment_like_count": 0, "bit_flags": 0, "created_at": 1538225865, "pk": 17951638531167221, "inline_composer_display_condition": "never", "status": "Active", "created_at_utc": 1538225865, "content_type": "comment", "has_liked_comment": false, "user": {"profile_pic_url": "https://scontent-sit4-1.cdninstagram.com/vp/cd8b0535a4f04ebc119e8bcaa69da824/5C493A8D/t51.2885-19/s150x150/32307799_197905477498136_6380179956932018176_n.jpg", "latest_reel_media": 1539603278, "profile_pic_id": "1786625579254421140_3440369418", "full_name": "Grey", "is_verified": false, "is_private": false, "username": "thania_grey", "pk": 3440369418}, "user_id": 3440369418, "type": 0, "did_report_as_spam": false}, {"text": "\ud83d\ude0d\ud83d\ude0d\ud83d\ude0d", "comment_like_count": 0, "bit_flags": 0, "created_at": 1538224025, "pk": 17876909428277595, "inline_composer_display_condition": "never", "status": "Active", "created_at_utc": 1538224025, "content_type": "comment", "has_liked_comment": false, "user": {"profile_pic_url": "https://scontent-sit4-1.cdninstagram.com/vp/34d4ccdebebc7e62de1ca74c62b8af8b/5C46AEBB/t51.2885-19/s150x150/25021945_1996777387202079_6576432534698065920_n.jpg", "latest_reel_media": 1539606181, "profile_pic_id": "1677015124228856320_311854635", "full_name": "Sisilia Dsi Maria S.S", "is_verified": false, "is_private": false, "username": "sisilia_dsi", "pk": 311854635}, "user_id": 311854635, "type": 0, "did_report_as_spam": false}, {"text": "\ud83d\ude0d\ud83d\ude0d", "comment_like_count": 0, "bit_flags": 0, "created_at": 1538221910, "pk": 17963172985088953, "inline_composer_display_condition": "never", "status": "Active", "created_at_utc": 1538221910, "content_type": "comment", "has_liked_comment": false, "user": {"profile_pic_url": "https://scontent-sit4-1.cdninstagram.com/vp/6f32ece2a17e1fde5563a4d9a8818a42/5C5E043B/t51.2885-19/s150x150/43279673_2255624984724680_3397100465761026048_n.jpg", "profile_pic_id": "1887578450479310753_1519564807", "full_name": "MakeupArtist & Endorsement \u269c\ufe0f", "is_verified": false, "is_private": false, "username": "tinaanqelin", "pk": 1519564807}, "user_id": 1519564807, "type": 0, "did_report_as_spam": false}], "age": "23"}