{"gender": "female", "comments": [{"content_type": "comment", "type": 2, "created_at_utc": 1539379982, "pk": 17959949200151776, "inline_composer_display_condition": "never", "status": "Active", "user_id": 178138871, "did_report_as_spam": false, "bit_flags": 0, "text": "@claralinanda jealous!!!", "created_at": 1539379982, "user": {"full_name": "Nadira Zahiruddin", "is_verified": false, "profile_pic_url": "https://scontent-sin6-2.cdninstagram.com/vp/05cf8ac69d8f24767ff19c3674fd9eb2/5C8AC76E/t51.2885-19/s150x150/27878626_416969415420093_2518246944640335872_n.jpg", "is_private": true, "pk": 178138871, "username": "coconadz", "profile_pic_id": "1612083186490145511_178138871"}}, {"content_type": "comment", "type": 0, "created_at_utc": 1539285394, "pk": 17880587917278537, "inline_composer_display_condition": "never", "status": "Active", "comment_like_count": 0, "has_liked_comment": false, "user_id": 871548853, "did_report_as_spam": false, "bit_flags": 0, "text": "\ud83d\udc86\ud83c\udffb\u200d\u2640\u2728\ud83d\ude0a", "created_at": 1539285394, "user": {"full_name": "My Cozy Room Boutique Spa", "is_verified": false, "profile_pic_url": "https://scontent-sin6-2.cdninstagram.com/vp/f2844be8559ed494024ae36e14b6cdef/5C62756A/t51.2885-19/11363985_1450873808554820_1133959641_a.jpg", "is_private": false, "pk": 871548853, "username": "mycozyroomspa"}}, {"content_type": "comment", "type": 0, "created_at_utc": 1539231876, "pk": 17964869845139789, "inline_composer_display_condition": "never", "status": "Active", "comment_like_count": 1, "has_liked_comment": false, "user_id": 9193078, "did_report_as_spam": false, "bit_flags": 0, "text": "Omg it\u2019s THE stuart weitzman!! @coconadz", "created_at": 1539231876, "user": {"full_name": "Clara Linanda", "is_verified": false, "profile_pic_url": "https://scontent-sin6-2.cdninstagram.com/vp/40df27850ed7000e3b9c83c8d90f1121/5C3D1B0C/t51.2885-19/s150x150/20066589_324270878014555_2967725760476872704_a.jpg", "is_private": true, "pk": 9193078, "username": "claralinanda", "profile_pic_id": "1561066314415981031_9193078"}}, {"content_type": "comment", "type": 2, "created_at_utc": 1539226721, "pk": 17880413722276432, "inline_composer_display_condition": "never", "status": "Active", "user_id": 422009532, "did_report_as_spam": false, "bit_flags": 0, "text": "@chelseanikkita you\u2019re an icon", "created_at": 1539226721, "user": {"full_name": "danielle victoriano", "is_verified": false, "profile_pic_url": "https://scontent-sin6-2.cdninstagram.com/vp/6a1f8798db407566e8b106386023d9c9/5C533EDD/t51.2885-19/s150x150/42122585_336070347163697_6274270762106880000_n.jpg", "is_private": true, "pk": 422009532, "username": "dvictoriano", "profile_pic_id": "1878062703635686889_422009532"}}, {"content_type": "comment", "type": 0, "created_at_utc": 1539224131, "pk": 17857159561290787, "inline_composer_display_condition": "never", "status": "Active", "comment_like_count": 1, "has_liked_comment": false, "user_id": 393033136, "did_report_as_spam": false, "bit_flags": 0, "text": "Inspiring\ud83d\ude4c\ud83c\udffe", "created_at": 1539224131, "user": {"full_name": "BAYO.", "is_verified": false, "profile_pic_url": "https://scontent-sin6-2.cdninstagram.com/vp/2a813dee4e4b8d06b339c7b13eba3725/5C5CAACA/t51.2885-19/s150x150/42068662_2079365812378004_2060919363833167872_n.jpg", "is_private": false, "pk": 393033136, "latest_reel_media": 1539641613, "username": "bayo_de", "profile_pic_id": "1862689610112173766_393033136"}}, {"content_type": "comment", "type": 0, "created_at_utc": 1539223416, "pk": 17952173470174293, "inline_composer_display_condition": "never", "status": "Active", "comment_like_count": 1, "has_liked_comment": false, "user_id": 1623648703, "did_report_as_spam": false, "bit_flags": 0, "text": "ask him for a job??!!\ud83d\udc40", "created_at": 1539223416, "user": {"full_name": "jp", "is_verified": false, "profile_pic_url": "https://scontent-sin6-2.cdninstagram.com/vp/321330fd83eab374adbe0a0d55c2eafe/5C49A0FF/t51.2885-19/s150x150/43354107_172983320298073_475198651963015168_n.jpg", "is_private": true, "pk": 1623648703, "username": "_jacquelinepan_", "profile_pic_id": "1888906079834512012_1623648703"}}, {"content_type": "comment", "type": 2, "created_at_utc": 1539223331, "pk": 17897208199253763, "inline_composer_display_condition": "never", "status": "Active", "user_id": 4228813, "did_report_as_spam": false, "bit_flags": 0, "text": "@mandyhey right?! \ud83e\udd29", "created_at": 1539223331, "user": {"full_name": "Chelsea N. Ng", "is_verified": false, "profile_pic_url": "https://scontent-sin6-2.cdninstagram.com/vp/e2cc1c936cc6d7f7aad1a2ca70bf95a1/5C5D3540/t51.2885-19/s150x150/41863723_1861661807287473_9005811151375695872_n.jpg", "is_private": false, "pk": 4228813, "latest_reel_media": 1539642571, "username": "chelseanikkita", "profile_pic_id": "1878699656940595388_4228813"}}, {"content_type": "comment", "type": 2, "created_at_utc": 1539223326, "pk": 17958509932150695, "inline_composer_display_condition": "never", "status": "Active", "user_id": 4228813, "did_report_as_spam": false, "bit_flags": 0, "text": "@alyssaaa.cai he\u2019s sooo inspiring! \u2728", "created_at": 1539223326, "user": {"full_name": "Chelsea N. Ng", "is_verified": false, "profile_pic_url": "https://scontent-sin6-2.cdninstagram.com/vp/e2cc1c936cc6d7f7aad1a2ca70bf95a1/5C5D3540/t51.2885-19/s150x150/41863723_1861661807287473_9005811151375695872_n.jpg", "is_private": false, "pk": 4228813, "latest_reel_media": 1539642571, "username": "chelseanikkita", "profile_pic_id": "1878699656940595388_4228813"}}, {"content_type": "comment", "type": 2, "created_at_utc": 1539223317, "pk": 17978750134072444, "inline_composer_display_condition": "never", "status": "Active", "user_id": 4228813, "did_report_as_spam": false, "bit_flags": 0, "text": "@amyzhang24 it did it did indeed\ud83d\ude48\ud83e\udd29\u2764\ufe0f", "created_at": 1539223317, "user": {"full_name": "Chelsea N. Ng", "is_verified": false, "profile_pic_url": "https://scontent-sin6-2.cdninstagram.com/vp/e2cc1c936cc6d7f7aad1a2ca70bf95a1/5C5D3540/t51.2885-19/s150x150/41863723_1861661807287473_9005811151375695872_n.jpg", "is_private": false, "pk": 4228813, "latest_reel_media": 1539642571, "username": "chelseanikkita", "profile_pic_id": "1878699656940595388_4228813"}}, {"content_type": "comment", "type": 0, "created_at_utc": 1539222760, "pk": 17955466192165943, "inline_composer_display_condition": "never", "status": "Active", "comment_like_count": 1, "has_liked_comment": false, "user_id": 265722797, "did_report_as_spam": false, "bit_flags": 0, "text": "What a legend wow", "created_at": 1539222760, "user": {"full_name": "Amanda Haye", "is_verified": false, "profile_pic_url": "https://scontent-sin6-2.cdninstagram.com/vp/a953f8b01ce370246585ca0694938d47/5C515B86/t51.2885-19/s150x150/21980969_541613276182822_289850150052954112_n.jpg", "is_private": true, "pk": 265722797, "username": "mandyhey", "profile_pic_id": "1613065207130882387_265722797"}}, {"content_type": "comment", "type": 0, "created_at_utc": 1539221015, "pk": 17897790664254590, "inline_composer_display_condition": "never", "status": "Active", "comment_like_count": 0, "has_liked_comment": false, "user_id": 1414415286, "did_report_as_spam": false, "bit_flags": 0, "text": "aww so happy this happened \u2764\ufe0f\u2764\ufe0f", "created_at": 1539221015, "user": {"full_name": "Amy Zhang", "is_verified": false, "profile_pic_url": "https://scontent-sin6-2.cdninstagram.com/vp/88a3028b6bb8091cca815b5ffb1d789c/5C4D0B8A/t51.2885-19/s150x150/23161229_254174338442716_9091515656104312832_n.jpg", "is_private": true, "pk": 1414415286, "username": "amyzhang24", "profile_pic_id": "1639687547586968952_1414415286"}}, {"content_type": "comment", "type": 2, "created_at_utc": 1539220868, "pk": 17973023557109673, "inline_composer_display_condition": "never", "status": "Active", "user_id": 4228813, "did_report_as_spam": false, "bit_flags": 0, "text": "@dvictoriano he was like \u201cwhere are you from?\u201d I was like \u201cINDONESIAAAA\u201d hahahahah \ud83d\ude27\ud83d\ude2f", "created_at": 1539220868, "user": {"full_name": "Chelsea N. Ng", "is_verified": false, "profile_pic_url": "https://scontent-sin6-2.cdninstagram.com/vp/e2cc1c936cc6d7f7aad1a2ca70bf95a1/5C5D3540/t51.2885-19/s150x150/41863723_1861661807287473_9005811151375695872_n.jpg", "is_private": false, "pk": 4228813, "latest_reel_media": 1539642571, "username": "chelseanikkita", "profile_pic_id": "1878699656940595388_4228813"}}, {"content_type": "comment", "type": 0, "created_at_utc": 1539220805, "pk": 17857103599291659, "inline_composer_display_condition": "never", "status": "Active", "comment_like_count": 0, "has_liked_comment": false, "user_id": 197806934, "did_report_as_spam": false, "bit_flags": 0, "text": "Omg amazinggg!!", "created_at": 1539220805, "user": {"full_name": "Alyssa Cai", "is_verified": false, "profile_pic_url": "https://scontent-sin6-2.cdninstagram.com/vp/052407a6df538d1610974d619b9aa3c9/5C43A550/t51.2885-19/s150x150/36159848_231435977463773_7694401707119214592_n.jpg", "is_private": false, "pk": 197806934, "latest_reel_media": 1539650451, "username": "alyssaaa.cai", "profile_pic_id": "1813228905369567235_197806934"}}, {"content_type": "comment", "type": 0, "created_at_utc": 1539219808, "pk": 17946203977199264, "inline_composer_display_condition": "never", "status": "Active", "comment_like_count": 0, "has_liked_comment": false, "user_id": 422009532, "did_report_as_spam": false, "bit_flags": 0, "text": "Omg goals", "created_at": 1539219808, "user": {"full_name": "danielle victoriano", "is_verified": false, "profile_pic_url": "https://scontent-sin6-2.cdninstagram.com/vp/6a1f8798db407566e8b106386023d9c9/5C533EDD/t51.2885-19/s150x150/42122585_336070347163697_6274270762106880000_n.jpg", "is_private": true, "pk": 422009532, "username": "dvictoriano", "profile_pic_id": "1878062703635686889_422009532"}}, {"content_type": "comment", "type": 2, "created_at_utc": 1539219647, "pk": 17982768652069970, "inline_composer_display_condition": "never", "status": "Active", "user_id": 4228813, "did_report_as_spam": false, "bit_flags": 0, "text": "@lucasrene_ hahahah I wish \ud83d\ude43", "created_at": 1539219647, "user": {"full_name": "Chelsea N. Ng", "is_verified": false, "profile_pic_url": "https://scontent-sin6-2.cdninstagram.com/vp/e2cc1c936cc6d7f7aad1a2ca70bf95a1/5C5D3540/t51.2885-19/s150x150/41863723_1861661807287473_9005811151375695872_n.jpg", "is_private": false, "pk": 4228813, "latest_reel_media": 1539642571, "username": "chelseanikkita", "profile_pic_id": "1878699656940595388_4228813"}}, {"content_type": "comment", "type": 0, "created_at_utc": 1539219601, "pk": 17972081056119161, "inline_composer_display_condition": "never", "status": "Active", "comment_like_count": 3, "has_liked_comment": false, "user_id": 1372548053, "did_report_as_spam": false, "bit_flags": 0, "text": "Two successful entrepreneurs", "created_at": 1539219601, "user": {"full_name": "Lucas Ren\u00e9", "is_verified": false, "profile_pic_url": "https://scontent-sin6-2.cdninstagram.com/vp/6c47c08de2970498e5c9af6a1dcd5d33/5C3FCEA1/t51.2885-19/s150x150/42487992_318190382315570_5443948043558715392_n.jpg", "is_private": true, "pk": 1372548053, "username": "lucasrene_", "profile_pic_id": "1889437554605658667_1372548053"}}], "age": "22", "user": "chelseanikkita"}