{"age": "23", "gender": "male", "comments": [{"created_at": 1527254281, "text": "Follback @dixiewang5", "user_id": 1952566667, "status": "Active", "bit_flags": 0, "content_type": "comment", "inline_composer_display_condition": "never", "has_liked_comment": false, "created_at_utc": 1527254281, "user": {"is_verified": false, "pk": 1952566667, "username": "cindy.arvisca", "is_private": true, "profile_pic_id": "1884928843985016290_1952566667", "full_name": "Cece", "profile_pic_url": "https://scontent-sit4-1.cdninstagram.com/vp/968f61db439f5aace8bf9d661d19a298/5C5A2B03/t51.2885-19/s150x150/42384995_241644536528848_7363520175414444032_n.jpg"}, "pk": 17947716568013424, "did_report_as_spam": false, "comment_like_count": 0, "type": 0}, {"created_at": 1513835766, "text": "Flbck\ud83d\ude0a", "user_id": 5892421535, "status": "Active", "bit_flags": 0, "content_type": "comment", "inline_composer_display_condition": "never", "has_liked_comment": false, "created_at_utc": 1513835766, "user": {"is_verified": false, "pk": 5892421535, "username": "strisiaaa", "is_private": false, "profile_pic_id": "1857432158320085241_5892421535", "full_name": "S i n d i \u2640 || Pontianak \ud83d\udccd", "profile_pic_url": "https://scontent-sit4-1.cdninstagram.com/vp/3181103a83ad6fd161bac0439ce3be0f/5C40503D/t51.2885-19/s150x150/39333326_1562153040556807_3555550257511137280_n.jpg"}, "pk": 17887333066151229, "did_report_as_spam": false, "comment_like_count": 0, "type": 0}, {"created_at": 1513748185, "text": "Follow back", "user_id": 708247687, "status": "Active", "bit_flags": 0, "content_type": "comment", "inline_composer_display_condition": "never", "has_liked_comment": false, "created_at_utc": 1513748185, "user": {"is_verified": false, "pk": 708247687, "username": "ikysasikome", "latest_reel_media": 1539592188, "is_private": false, "profile_pic_id": "1706502540680449119_708247687", "full_name": "I K Y", "profile_pic_url": "https://scontent-sit4-1.cdninstagram.com/vp/445e1f9b1b0a8336be2d8c526b36c92d/5C54E403/t51.2885-19/s150x150/26868891_294957607696747_8094154022962855936_n.jpg"}, "pk": 17913294070004098, "did_report_as_spam": false, "comment_like_count": 0, "type": 0}, {"created_at": 1513739833, "text": "follback kak\ud83d\ude0a", "user_id": 5352115322, "status": "Active", "bit_flags": 0, "content_type": "comment", "inline_composer_display_condition": "never", "has_liked_comment": false, "created_at_utc": 1513739833, "user": {"is_verified": false, "pk": 5352115322, "username": "_chikanrsptd", "is_private": false, "profile_pic_id": "1848468933801473020_5352115322", "full_name": "Chika Naraspati", "profile_pic_url": "https://scontent-sit4-1.cdninstagram.com/vp/25af21b6d6c0fe656a8da9d446017cca/5C501515/t51.2885-19/s150x150/39523518_2190894167604936_3316488624014360576_n.jpg"}, "pk": 17899342996123529, "did_report_as_spam": false, "comment_like_count": 0, "type": 0}, {"created_at": 1513701798, "text": "Mohon cechk DM inbox nya ada tawaran job foto @dixiewang5 thanks", "user_id": 314586142, "status": "Active", "bit_flags": 0, "content_type": "comment", "inline_composer_display_condition": "never", "has_liked_comment": false, "created_at_utc": 1513701798, "user": {"is_verified": false, "pk": 314586142, "username": "brm.subiandinata", "is_private": true, "profile_pic_id": "1453039932464560742_314586142", "full_name": "BRM Subiandinata", "profile_pic_url": "https://scontent-sit4-1.cdninstagram.com/vp/607776159ff38adcff35aa6e0c7b6129/5C50352B/t51.2885-19/s150x150/16465004_1299985163378092_1361921017026445312_a.jpg"}, "pk": 17899023199124124, "did_report_as_spam": false, "comment_like_count": 0, "type": 0}, {"created_at": 1513669215, "text": "Follbck\ud83d\ude0a", "user_id": 1431743033, "status": "Active", "bit_flags": 0, "content_type": "comment", "inline_composer_display_condition": "never", "has_liked_comment": false, "created_at_utc": 1513669215, "user": {"is_verified": false, "pk": 1431743033, "username": "devitagunawan_", "is_private": false, "profile_pic_id": "1887109122743133544_1431743033", "full_name": "devitaa", "profile_pic_url": "https://scontent-sit4-1.cdninstagram.com/vp/9ec88115c16edd60f25ec94d9aba242f/5C62967D/t51.2885-19/s150x150/42068662_2012915955396014_7219524314414972928_n.jpg"}, "pk": 17854475125208284, "did_report_as_spam": false, "comment_like_count": 0, "type": 0}, {"created_at": 1513642465, "text": "@basketballdailydose \ud83d\udc4c\ud83c\udffc\ud83d\udc4c\ud83c\udffc\ud83d\udc4c\ud83c\udffc hebat masih muda kuat naik gunung", "user_id": 330834607, "status": "Active", "bit_flags": 0, "content_type": "comment", "inline_composer_display_condition": "never", "created_at_utc": 1513642465, "user": {"is_verified": false, "pk": 330834607, "username": "cerelia_chandra", "is_private": true, "profile_pic_id": "1840749738792336965_330834607", "full_name": "Cerelia Chandra", "profile_pic_url": "https://scontent-sit4-1.cdninstagram.com/vp/138236f236f8b55b4e5f2e22bd51f3ec/5C6152A2/t51.2885-19/s150x150/38072700_247451882566466_5995001349886967808_n.jpg"}, "pk": 17896603231083767, "did_report_as_spam": false, "type": 2}, {"created_at": 1513616322, "text": "@mumpuni12 kgk kok", "user_id": 350559813, "status": "Active", "bit_flags": 0, "content_type": "comment", "inline_composer_display_condition": "never", "created_at_utc": 1513616322, "user": {"is_verified": false, "pk": 350559813, "username": "dixiewang5", "is_private": false, "profile_pic_id": "1865689824921478926_350559813", "full_name": "Phil 4:19", "profile_pic_url": "https://scontent-sit4-1.cdninstagram.com/vp/86d3ff13369ae7efdf01c2d70a5b49fc/5C44B51D/t51.2885-19/s150x150/41456526_347696559303148_2105794784164577280_n.jpg"}, "pk": 17900586832097332, "did_report_as_spam": false, "type": 2}, {"created_at": 1513615886, "text": "Bedeh @cerelia_chandra", "user_id": 6250309930, "status": "Active", "bit_flags": 0, "content_type": "comment", "inline_composer_display_condition": "never", "has_liked_comment": false, "created_at_utc": 1513615886, "user": {"is_verified": false, "pk": 6250309930, "username": "basketballdailydose", "latest_reel_media": 1539618387, "is_private": false, "profile_pic_id": "1882893753775921122_6250309930", "full_name": "Basketball Daily Dose #BDD", "profile_pic_url": "https://scontent-sit4-1.cdninstagram.com/vp/07fe441c49674fc55f0c491bcf612b35/5C5229D1/t51.2885-19/s150x150/42941013_161865888077594_3414992393278062592_n.jpg"}, "pk": 17914476091003068, "did_report_as_spam": false, "comment_like_count": 0, "type": 0}, {"created_at": 1513615107, "text": "Cuaca bukannya lagi buruk ya, rawan longsor?", "user_id": 1360331772, "status": "Active", "bit_flags": 0, "content_type": "comment", "inline_composer_display_condition": "never", "has_liked_comment": false, "created_at_utc": 1513615107, "user": {"is_verified": false, "pk": 1360331772, "username": "mumpuni12", "is_private": true, "profile_pic_id": "1887377402724769065_1360331772", "full_name": "\u30e6\u30cb\u30a2\u30eb \u30e0\u30e0\u3077\u306b", "profile_pic_url": "https://scontent-sit4-1.cdninstagram.com/vp/1672fa7ec15ff3d3259ca2eee1ba1aca/5C461A82/t51.2885-19/s150x150/43634606_1192107887623185_1973311063310991360_n.jpg"}, "pk": 17900658940111150, "did_report_as_spam": false, "comment_like_count": 0, "type": 0}, {"created_at": 1513615051, "text": "@mumpuni12 yoks", "user_id": 350559813, "status": "Active", "bit_flags": 0, "content_type": "comment", "inline_composer_display_condition": "never", "created_at_utc": 1513615051, "user": {"is_verified": false, "pk": 350559813, "username": "dixiewang5", "is_private": false, "profile_pic_id": "1865689824921478926_350559813", "full_name": "Phil 4:19", "profile_pic_url": "https://scontent-sit4-1.cdninstagram.com/vp/86d3ff13369ae7efdf01c2d70a5b49fc/5C44B51D/t51.2885-19/s150x150/41456526_347696559303148_2105794784164577280_n.jpg"}, "pk": 17908208305071979, "did_report_as_spam": false, "type": 2}, {"created_at": 1513615025, "text": "Gokiill anak gunung \ud83d\udc4f", "user_id": 1360331772, "status": "Active", "bit_flags": 0, "content_type": "comment", "inline_composer_display_condition": "never", "has_liked_comment": false, "created_at_utc": 1513615025, "user": {"is_verified": false, "pk": 1360331772, "username": "mumpuni12", "is_private": true, "profile_pic_id": "1887377402724769065_1360331772", "full_name": "\u30e6\u30cb\u30a2\u30eb \u30e0\u30e0\u3077\u306b", "profile_pic_url": "https://scontent-sit4-1.cdninstagram.com/vp/1672fa7ec15ff3d3259ca2eee1ba1aca/5C461A82/t51.2885-19/s150x150/43634606_1192107887623185_1973311063310991360_n.jpg"}, "pk": 17883770275173551, "did_report_as_spam": false, "comment_like_count": 0, "type": 0}], "user": "dixiewang5"}