{"user": "abigail.anastasia", "comments": [{"user": {"profile_pic_id": "1876268813915171198_3946430560", "profile_pic_url": "https://scontent-sin6-2.cdninstagram.com/vp/191f9786763945b7d82c05692b9d569a/5C560879/t51.2885-19/s150x150/41578497_314352059367363_7619959942375538688_n.jpg", "is_verified": false, "is_private": true, "username": "itsbaxterhyper", "full_name": "Baxter Chua", "pk": 3946430560}, "user_id": 3946430560, "inline_composer_display_condition": "never", "comment_like_count": 0, "has_liked_comment": false, "content_type": "comment", "bit_flags": 0, "pk": 17861996542051069, "status": "Active", "text": "Abigail!!", "created_at": 1474630421, "type": 0, "created_at_utc": 1474630421, "did_report_as_spam": false}, {"user": {"profile_pic_id": "1889813267247145283_1604953537", "profile_pic_url": "https://scontent-sin6-2.cdninstagram.com/vp/4af0d1761b6694f3f9a513e8a1f0d58c/5C5315C5/t51.2885-19/s150x150/42135257_505504419955657_2729819782420365312_n.jpg", "is_verified": false, "is_private": false, "username": "leandravincii", "full_name": "", "pk": 1604953537}, "user_id": 1604953537, "inline_composer_display_condition": "never", "comment_like_count": 0, "has_liked_comment": false, "content_type": "comment", "bit_flags": 0, "pk": 17859888736051069, "status": "Active", "text": "Luckyyyy", "created_at": 1471417566, "type": 0, "created_at_utc": 1471417566, "did_report_as_spam": false}, {"user": {"profile_pic_id": "1889813267247145283_1604953537", "profile_pic_url": "https://scontent-sin6-2.cdninstagram.com/vp/4af0d1761b6694f3f9a513e8a1f0d58c/5C5315C5/t51.2885-19/s150x150/42135257_505504419955657_2729819782420365312_n.jpg", "is_verified": false, "is_private": false, "username": "leandravincii", "full_name": "", "pk": 1604953537}, "user_id": 1604953537, "inline_composer_display_condition": "never", "comment_like_count": 0, "has_liked_comment": false, "content_type": "comment", "bit_flags": 0, "pk": 17860873636019394, "status": "Active", "text": "@felicia_naomi_1414 DM MEE", "created_at": 1470582858, "type": 0, "created_at_utc": 1470582858, "did_report_as_spam": false}, {"user": {"profile_pic_id": "1878867550374714417_2080188130", "profile_pic_url": "https://scontent-sin6-2.cdninstagram.com/vp/5ed9cffba7f4d84df8758d4ca503e122/5C4AD623/t51.2885-19/s150x150/41775975_773684272963907_3127153718143746048_n.jpg", "is_verified": false, "is_private": false, "username": "fnclife", "latest_reel_media": 1539618472, "full_name": "\u0493\u1d07\u029f\u026a\u1d04\u026a\u1d00 \u0274\u1d00\u1d0f\u1d0d\u026a  \ud83d\udc9a\ud83d\udc7d", "pk": 2080188130}, "user_id": 2080188130, "inline_composer_display_condition": "never", "comment_like_count": 0, "has_liked_comment": false, "content_type": "comment", "bit_flags": 0, "pk": 17860873621019394, "status": "Active", "text": "@leandravinci_lps__ lucky why ???", "created_at": 1470582839, "type": 0, "created_at_utc": 1470582839, "did_report_as_spam": false}, {"user": {"profile_pic_id": "1889813267247145283_1604953537", "profile_pic_url": "https://scontent-sin6-2.cdninstagram.com/vp/4af0d1761b6694f3f9a513e8a1f0d58c/5C5315C5/t51.2885-19/s150x150/42135257_505504419955657_2729819782420365312_n.jpg", "is_verified": false, "is_private": false, "username": "leandravincii", "full_name": "", "pk": 1604953537}, "user_id": 1604953537, "inline_composer_display_condition": "never", "comment_like_count": 0, "has_liked_comment": false, "content_type": "comment", "bit_flags": 0, "pk": 17860873603019394, "status": "Active", "text": "@felicia_naomi_1414 u luckyyy", "created_at": 1470582802, "type": 0, "created_at_utc": 1470582802, "did_report_as_spam": false}, {"user": {"profile_pic_id": "1878867550374714417_2080188130", "profile_pic_url": "https://scontent-sin6-2.cdninstagram.com/vp/5ed9cffba7f4d84df8758d4ca503e122/5C4AD623/t51.2885-19/s150x150/41775975_773684272963907_3127153718143746048_n.jpg", "is_verified": false, "is_private": false, "username": "fnclife", "latest_reel_media": 1539618472, "full_name": "\u0493\u1d07\u029f\u026a\u1d04\u026a\u1d00 \u0274\u1d00\u1d0f\u1d0d\u026a  \ud83d\udc9a\ud83d\udc7d", "pk": 2080188130}, "user_id": 2080188130, "inline_composer_display_condition": "never", "comment_like_count": 0, "has_liked_comment": false, "content_type": "comment", "bit_flags": 0, "pk": 17860873381019394, "status": "Active", "text": "Very lucky \ud83d\ude22\ud83d\ude2d", "created_at": 1470582553, "type": 0, "created_at_utc": 1470582553, "did_report_as_spam": false}, {"user": {"profile_pic_id": "1889813267247145283_1604953537", "profile_pic_url": "https://scontent-sin6-2.cdninstagram.com/vp/4af0d1761b6694f3f9a513e8a1f0d58c/5C5315C5/t51.2885-19/s150x150/42135257_505504419955657_2729819782420365312_n.jpg", "is_verified": false, "is_private": false, "username": "leandravincii", "full_name": "", "pk": 1604953537}, "user_id": 1604953537, "inline_composer_display_condition": "never", "comment_like_count": 0, "has_liked_comment": false, "content_type": "comment", "bit_flags": 0, "pk": 17860873111019394, "status": "Active", "text": "luckyyy", "created_at": 1470582112, "type": 0, "created_at_utc": 1470582112, "did_report_as_spam": false}, {"user": {"profile_pic_id": "1871526974985290338_1286560802", "profile_pic_url": "https://scontent-sin6-2.cdninstagram.com/vp/87fee6e93da28ee8e035870755376ccb/5C5D3795/t51.2885-19/s150x150/40168568_338678413541959_5504454271514443776_n.jpg", "is_verified": false, "is_private": false, "username": "vanila_skies", "full_name": "Mother Of 9 Doggoz", "pk": 1286560802}, "user_id": 1286560802, "inline_composer_display_condition": "never", "comment_like_count": 0, "has_liked_comment": false, "content_type": "comment", "bit_flags": 0, "pk": 17860359994056938, "status": "Active", "text": "St moritz @abigail.anastasia", "created_at": 1470749814, "type": 0, "created_at_utc": 1470749814, "did_report_as_spam": false}, {"user": {"profile_pic_id": "1871526974985290338_1286560802", "profile_pic_url": "https://scontent-sin6-2.cdninstagram.com/vp/87fee6e93da28ee8e035870755376ccb/5C5D3795/t51.2885-19/s150x150/40168568_338678413541959_5504454271514443776_n.jpg", "is_verified": false, "is_private": false, "username": "vanila_skies", "full_name": "Mother Of 9 Doggoz", "pk": 1286560802}, "user_id": 1286560802, "inline_composer_display_condition": "never", "comment_like_count": 0, "has_liked_comment": false, "content_type": "comment", "bit_flags": 0, "pk": 17850558460072868, "status": "Active", "text": "@abigail.anastasia", "created_at": 1469201251, "type": 0, "created_at_utc": 1469201251, "did_report_as_spam": false}, {"user": {"profile_pic_id": "1871526974985290338_1286560802", "profile_pic_url": "https://scontent-sin6-2.cdninstagram.com/vp/87fee6e93da28ee8e035870755376ccb/5C5D3795/t51.2885-19/s150x150/40168568_338678413541959_5504454271514443776_n.jpg", "is_verified": false, "is_private": false, "username": "vanila_skies", "full_name": "Mother Of 9 Doggoz", "pk": 1286560802}, "user_id": 1286560802, "inline_composer_display_condition": "never", "comment_like_count": 0, "has_liked_comment": false, "content_type": "comment", "bit_flags": 0, "pk": 17850552157072868, "status": "Active", "text": "What is your musically ?", "created_at": 1469187928, "type": 0, "created_at_utc": 1469187928, "did_report_as_spam": false}, {"user": {"profile_pic_id": "1311163683401167456_3405587072", "profile_pic_url": "https://scontent-sin6-2.cdninstagram.com/vp/22761e4f0144df7829d16b10ee7a035f/5C5291BE/t51.2885-19/s150x150/13652017_1627834234193397_1678419370_a.jpg", "is_verified": false, "is_private": false, "username": "ccapacia", "full_name": "Ching Capacia", "pk": 3405587072}, "user_id": 3405587072, "inline_composer_display_condition": "never", "comment_like_count": 0, "has_liked_comment": false, "content_type": "comment", "bit_flags": 0, "pk": 17852489113066120, "status": "Active", "text": "See u on monday", "created_at": 1469189368, "type": 0, "created_at_utc": 1469189368, "did_report_as_spam": false}, {"user": {"profile_pic_id": "1311163683401167456_3405587072", "profile_pic_url": "https://scontent-sin6-2.cdninstagram.com/vp/22761e4f0144df7829d16b10ee7a035f/5C5291BE/t51.2885-19/s150x150/13652017_1627834234193397_1678419370_a.jpg", "is_verified": false, "is_private": false, "username": "ccapacia", "full_name": "Ching Capacia", "pk": 3405587072}, "user_id": 3405587072, "inline_composer_display_condition": "never", "comment_like_count": 0, "has_liked_comment": false, "content_type": "comment", "bit_flags": 0, "pk": 17852489101066120, "status": "Active", "text": "Hello abigail", "created_at": 1469189355, "type": 0, "created_at_utc": 1469189355, "did_report_as_spam": false}, {"user": {"profile_pic_id": "1889920582231120580_1298766623", "profile_pic_url": "https://scontent-sin6-2.cdninstagram.com/vp/7edc26bc64d5f0a64fd119493cda4fd0/5C510891/t51.2885-19/s150x150/42625677_178112803090889_5820002048417988608_n.jpg", "is_verified": false, "is_private": true, "username": "yulikapau", "full_name": "\u254b\u254b\u1d52\u01d2\u1d56\u00eb  \u03af\u01ae  \u011f\u01d2\u00ebs  S\u264d\u01d2\u01d2\u01ae\u1d34\u2113\u01b4..\ud83d\ude4f", "pk": 1298766623}, "user_id": 1298766623, "inline_composer_display_condition": "never", "comment_like_count": 0, "has_liked_comment": false, "content_type": "comment", "bit_flags": 0, "pk": 17852403412066120, "status": "Active", "text": "@abigail.anastasia ngakak wkakaka\ud83d\ude04\ud83d\ude04", "created_at": 1468995472, "type": 0, "created_at_utc": 1468995472, "did_report_as_spam": false}, {"user": {"profile_pic_id": "1297765978961055498_1980651827", "profile_pic_url": "https://scontent-sin6-2.cdninstagram.com/vp/2af674660fc606deb05a0ad94a0357f9/5C488CD7/t51.2885-19/s150x150/13712348_1183071898391624_2062428159_a.jpg", "is_verified": false, "is_private": false, "username": "abigail.anastasia", "full_name": "Abigail Anastasia Lie", "pk": 1980651827}, "user_id": 1980651827, "inline_composer_display_condition": "never", "comment_like_count": 0, "has_liked_comment": false, "content_type": "comment", "bit_flags": 0, "pk": 17859790357056967, "status": "Active", "text": "\ud83d\ude00\ud83d\ude00\ud83d\ude00", "created_at": 1469001072, "type": 0, "created_at_utc": 1469001072, "did_report_as_spam": false}, {"user": {"profile_pic_id": "1889920582231120580_1298766623", "profile_pic_url": "https://scontent-sin6-2.cdninstagram.com/vp/7edc26bc64d5f0a64fd119493cda4fd0/5C510891/t51.2885-19/s150x150/42625677_178112803090889_5820002048417988608_n.jpg", "is_verified": false, "is_private": true, "username": "yulikapau", "full_name": "\u254b\u254b\u1d52\u01d2\u1d56\u00eb  \u03af\u01ae  \u011f\u01d2\u00ebs  S\u264d\u01d2\u01d2\u01ae\u1d34\u2113\u01b4..\ud83d\ude4f", "pk": 1298766623}, "user_id": 1298766623, "inline_composer_display_condition": "never", "comment_like_count": 0, "has_liked_comment": false, "content_type": "comment", "bit_flags": 0, "pk": 17859788932056967, "status": "Active", "text": "@abigail.anastasia  hadeh bigel ngakak \ud83d\ude04\ud83d\ude04\ud83d\ude02", "created_at": 1468995507, "type": 0, "created_at_utc": 1468995507, "did_report_as_spam": false}], "age": "10", "gender": "female"}